{
  "fuente": "ESPN Argentina",
  "metodo": "scoreboard + summary doble endpoint paralelo",
  "fecha_scrapeo": "2026-05-04T19:39:14.001683-03:00",
  "total": 33,
  "total_ligas_consultadas": 116,
  "partidos": [
    {
      "id": "740940",
      "partido": "Chelsea vs Nottingham Forest",
      "local": "Chelsea",
      "visitante": "Nottingham Forest",
      "local_id": "363",
      "visitante_id": "393",
      "local_logo": "https://a.espncdn.com/i/teamlogos/soccer/500/363.png",
      "visitante_logo": "https://a.espncdn.com/i/teamlogos/soccer/500/393.png",
      "liga": "Premier League",
      "liga_corta": "Premier League",
      "liga_slug": "eng.1",
      "prioridad_liga": 20,
      "competicion": {
        "nombre": "Premier League",
        "nombre_corto": "Premier League",
        "slug": "eng.1",
        "prioridad": 20
      },
      "fecha": "2026-05-04",
      "hora_inicio": "11:00",
      "hora": "Fin",
      "mostrar_tiempo": "Fin",
      "estado": "Tiempo Completo",
      "estado_corto": "F",
      "estado_nombre": "STATUS_FULL_TIME",
      "completado": true,
      "minuto": null,
      "periodo": null,
      "marcador_local": "1",
      "marcador_visitante": "3",
      "resultado": "1-3",
      "mostrar_marcador": true,
      "goleadores": [],
      "fecha_espn": "2026-05-04T14:00Z",
      "url_espn": "https://www.espn.com.ar/futbol/partido/_/juegoId/740940/nottingham-forest-chelsea"
    },
    {
      "id": "740941",
      "partido": "Everton vs Manchester City",
      "local": "Everton",
      "visitante": "Manchester City",
      "local_id": "368",
      "visitante_id": "382",
      "local_logo": "https://a.espncdn.com/i/teamlogos/soccer/500/368.png",
      "visitante_logo": "https://a.espncdn.com/i/teamlogos/soccer/500/382.png",
      "liga": "Premier League",
      "liga_corta": "Premier League",
      "liga_slug": "eng.1",
      "prioridad_liga": 20,
      "competicion": {
        "nombre": "Premier League",
        "nombre_corto": "Premier League",
        "slug": "eng.1",
        "prioridad": 20
      },
      "fecha": "2026-05-04",
      "hora_inicio": "16:00",
      "hora": "Fin",
      "mostrar_tiempo": "Fin",
      "estado": "Tiempo Completo",
      "estado_corto": "F",
      "estado_nombre": "STATUS_FULL_TIME",
      "completado": true,
      "minuto": null,
      "periodo": null,
      "marcador_local": "3",
      "marcador_visitante": "3",
      "resultado": "3-3",
      "mostrar_marcador": true,
      "goleadores": [],
      "fecha_espn": "2026-05-04T19:00Z",
      "url_espn": "https://www.espn.com.ar/futbol/partido/_/juegoId/740941/manchester-city-everton"
    },
    {
      "id": "748478",
      "partido": "Sevilla FC vs Real Sociedad",
      "local": "Sevilla FC",
      "visitante": "Real Sociedad",
      "local_id": "243",
      "visitante_id": "89",
      "local_logo": "https://a.espncdn.com/i/teamlogos/soccer/500/243.png",
      "visitante_logo": "https://a.espncdn.com/i/teamlogos/soccer/500/89.png",
      "liga": "LaLiga",
      "liga_corta": "LaLiga",
      "liga_slug": "esp.1",
      "prioridad_liga": 21,
      "competicion": {
        "nombre": "LaLiga",
        "nombre_corto": "LaLiga",
        "slug": "esp.1",
        "prioridad": 21
      },
      "fecha": "2026-05-04",
      "hora_inicio": "16:00",
      "hora": "Fin",
      "mostrar_tiempo": "Fin",
      "estado": "Tiempo Completo",
      "estado_corto": "F",
      "estado_nombre": "STATUS_FULL_TIME",
      "completado": true,
      "minuto": null,
      "periodo": null,
      "marcador_local": "1",
      "marcador_visitante": "0",
      "resultado": "1-0",
      "mostrar_marcador": true,
      "goleadores": [],
      "fecha_espn": "2026-05-04T19:00Z",
      "url_espn": "https://www.espn.com.ar/futbol/partido/_/juegoId/748478/real-sociedad-sevilla"
    },
    {
      "id": "737129",
      "partido": "Cremonese vs Lazio",
      "local": "Cremonese",
      "visitante": "Lazio",
      "local_id": "4050",
      "visitante_id": "112",
      "local_logo": "https://a.espncdn.com/i/teamlogos/soccer/500/4050.png",
      "visitante_logo": "https://a.espncdn.com/i/teamlogos/soccer/500/112.png",
      "liga": "Serie A",
      "liga_corta": "Serie A",
      "liga_slug": "ita.1",
      "prioridad_liga": 22,
      "competicion": {
        "nombre": "Serie A",
        "nombre_corto": "Serie A",
        "slug": "ita.1",
        "prioridad": 22
      },
      "fecha": "2026-05-04",
      "hora_inicio": "13:30",
      "hora": "Fin",
      "mostrar_tiempo": "Fin",
      "estado": "Tiempo Completo",
      "estado_corto": "F",
      "estado_nombre": "STATUS_FULL_TIME",
      "completado": true,
      "minuto": null,
      "periodo": null,
      "marcador_local": "1",
      "marcador_visitante": "2",
      "resultado": "1-2",
      "mostrar_marcador": true,
      "goleadores": [],
      "fecha_espn": "2026-05-04T16:30Z",
      "url_espn": "https://www.espn.com.ar/futbol/partido/_/juegoId/737129/lazio-cremonese"
    },
    {
      "id": "737125",
      "partido": "AS Roma vs Fiorentina",
      "local": "AS Roma",
      "visitante": "Fiorentina",
      "local_id": "104",
      "visitante_id": "109",
      "local_logo": "https://a.espncdn.com/i/teamlogos/soccer/500/104.png",
      "visitante_logo": "https://a.espncdn.com/i/teamlogos/soccer/500/109.png",
      "liga": "Serie A",
      "liga_corta": "Serie A",
      "liga_slug": "ita.1",
      "prioridad_liga": 22,
      "competicion": {
        "nombre": "Serie A",
        "nombre_corto": "Serie A",
        "slug": "ita.1",
        "prioridad": 22
      },
      "fecha": "2026-05-04",
      "hora_inicio": "15:45",
      "hora": "Fin",
      "mostrar_tiempo": "Fin",
      "estado": "Tiempo Completo",
      "estado_corto": "F",
      "estado_nombre": "STATUS_FULL_TIME",
      "completado": true,
      "minuto": null,
      "periodo": null,
      "marcador_local": "4",
      "marcador_visitante": "0",
      "resultado": "4-0",
      "mostrar_marcador": true,
      "goleadores": [],
      "fecha_espn": "2026-05-04T18:45Z",
      "url_espn": "https://www.espn.com.ar/futbol/partido/_/juegoId/737125/fiorentina-as-roma"
    },
    {
      "id": "748933",
      "partido": "Almería vs Mirandés",
      "local": "Almería",
      "visitante": "Mirandés",
      "local_id": "6832",
      "visitante_id": "4515",
      "local_logo": "https://a.espncdn.com/i/teamlogos/soccer/500/6832.png",
      "visitante_logo": "https://a.espncdn.com/i/teamlogos/soccer/500/4515.png",
      "liga": "LaLiga 2",
      "liga_corta": "LaLiga 2",
      "liga_slug": "esp.2",
      "prioridad_liga": 36,
      "competicion": {
        "nombre": "LaLiga 2",
        "nombre_corto": "LaLiga 2",
        "slug": "esp.2",
        "prioridad": 36
      },
      "fecha": "2026-05-04",
      "hora_inicio": "15:30",
      "hora": "Fin",
      "mostrar_tiempo": "Fin",
      "estado": "Tiempo Completo",
      "estado_corto": "F",
      "estado_nombre": "STATUS_FULL_TIME",
      "completado": true,
      "minuto": null,
      "periodo": null,
      "marcador_local": "4",
      "marcador_visitante": "2",
      "resultado": "4-2",
      "mostrar_marcador": true,
      "goleadores": [],
      "fecha_espn": "2026-05-04T18:30Z",
      "url_espn": "https://www.espn.com.ar/futbol/partido/_/juegoId/748933/mirandes-almeria"
    },
    {
      "id": "750530",
      "partido": "Sporting CP vs Vitória de Guimaraes",
      "local": "Sporting CP",
      "visitante": "Vitória de Guimaraes",
      "local_id": "2250",
      "visitante_id": "5309",
      "local_logo": "https://a.espncdn.com/i/teamlogos/soccer/500/2250.png",
      "visitante_logo": "https://a.espncdn.com/i/teamlogos/soccer/500/5309.png",
      "liga": "Primeira Liga",
      "liga_corta": "Primeira Liga",
      "liga_slug": "por.1",
      "prioridad_liga": 50,
      "competicion": {
        "nombre": "Primeira Liga",
        "nombre_corto": "Primeira Liga",
        "slug": "por.1",
        "prioridad": 50
      },
      "fecha": "2026-05-04",
      "hora_inicio": "16:15",
      "hora": "Fin",
      "mostrar_tiempo": "Fin",
      "estado": "Tiempo Completo",
      "estado_corto": "F",
      "estado_nombre": "STATUS_FULL_TIME",
      "completado": true,
      "minuto": null,
      "periodo": null,
      "marcador_local": "5",
      "marcador_visitante": "1",
      "resultado": "5-1",
      "mostrar_marcador": true,
      "goleadores": [],
      "fecha_espn": "2026-05-04T19:15Z",
      "url_espn": "https://www.espn.com.ar/futbol/partido/_/juegoId/750530/vitoria-de-guimaraes-sporting-cp"
    },
    {
      "id": "401867706",
      "partido": "Heart of Midlothian vs Rangers",
      "local": "Heart of Midlothian",
      "visitante": "Rangers",
      "local_id": "262",
      "visitante_id": "257",
      "local_logo": "https://a.espncdn.com/i/teamlogos/soccer/500/262.png",
      "visitante_logo": "https://a.espncdn.com/i/teamlogos/soccer/500/257.png",
      "liga": "Scottish Premiership",
      "liga_corta": "Scottish Premiership",
      "liga_slug": "sco.1",
      "prioridad_liga": 54,
      "competicion": {
        "nombre": "Scottish Premiership",
        "nombre_corto": "Scottish Premiership",
        "slug": "sco.1",
        "prioridad": 54
      },
      "fecha": "2026-05-04",
      "hora_inicio": "13:30",
      "hora": "Fin",
      "mostrar_tiempo": "Fin",
      "estado": "Tiempo Completo",
      "estado_corto": "F",
      "estado_nombre": "STATUS_FULL_TIME",
      "completado": true,
      "minuto": null,
      "periodo": null,
      "marcador_local": "2",
      "marcador_visitante": "1",
      "resultado": "2-1",
      "mostrar_marcador": true,
      "goleadores": [],
      "fecha_espn": "2026-05-04T16:30Z",
      "url_espn": "https://www.espn.com.ar/futbol/partido/_/juegoId/401867706/rangers-heart-of-midlothian"
    },
    {
      "id": "401864042",
      "partido": "SC Rheindorf Altach vs Wolfsberger",
      "local": "SC Rheindorf Altach",
      "visitante": "Wolfsberger",
      "local_id": "4405",
      "visitante_id": "13294",
      "local_logo": "https://a.espncdn.com/i/teamlogos/soccer/500/4405.png",
      "visitante_logo": "https://a.espncdn.com/i/teamlogos/soccer/500/13294.png",
      "liga": "Austrian Bundesliga",
      "liga_corta": "Austrian Bundesliga",
      "liga_slug": "aut.1",
      "prioridad_liga": 55,
      "competicion": {
        "nombre": "Austrian Bundesliga",
        "nombre_corto": "Austrian Bundesliga",
        "slug": "aut.1",
        "prioridad": 55
      },
      "fecha": "2026-05-04",
      "hora_inicio": "13:30",
      "hora": "Fin",
      "mostrar_tiempo": "Fin",
      "estado": "Tiempo Completo",
      "estado_corto": "F",
      "estado_nombre": "STATUS_FULL_TIME",
      "completado": true,
      "minuto": null,
      "periodo": null,
      "marcador_local": "1",
      "marcador_visitante": "4",
      "resultado": "1-4",
      "mostrar_marcador": true,
      "goleadores": [],
      "fecha_espn": "2026-05-04T16:30Z",
      "url_espn": "https://www.espn.com.ar/futbol/partido/_/juegoId/401864042/wolfsberger-sc-rheindorf-altach"
    },
    {
      "id": "401864040",
      "partido": "LASK Linz vs Rapid Vienna",
      "local": "LASK Linz",
      "visitante": "Rapid Vienna",
      "local_id": "4411",
      "visitante_id": "519",
      "local_logo": "https://a.espncdn.com/i/teamlogos/soccer/500/4411.png",
      "visitante_logo": "https://a.espncdn.com/i/teamlogos/soccer/500/519.png",
      "liga": "Austrian Bundesliga",
      "liga_corta": "Austrian Bundesliga",
      "liga_slug": "aut.1",
      "prioridad_liga": 55,
      "competicion": {
        "nombre": "Austrian Bundesliga",
        "nombre_corto": "Austrian Bundesliga",
        "slug": "aut.1",
        "prioridad": 55
      },
      "fecha": "2026-05-04",
      "hora_inicio": "15:30",
      "hora": "Fin",
      "mostrar_tiempo": "Fin",
      "estado": "Tiempo Completo",
      "estado_corto": "F",
      "estado_nombre": "STATUS_FULL_TIME",
      "completado": true,
      "minuto": null,
      "periodo": null,
      "marcador_local": "3",
      "marcador_visitante": "1",
      "resultado": "3-1",
      "mostrar_marcador": true,
      "goleadores": [],
      "fecha_espn": "2026-05-04T18:30Z",
      "url_espn": "https://www.espn.com.ar/futbol/partido/_/juegoId/401864040"
    },
    {
      "id": "401860124",
      "partido": "Vila Nova vs Athletic",
      "local": "Vila Nova",
      "visitante": "Athletic",
      "local_id": "9973",
      "visitante_id": "20851",
      "local_logo": "https://a.espncdn.com/i/teamlogos/soccer/500/9973.png",
      "visitante_logo": "https://a.espncdn.com/i/teamlogos/soccer/500/20851.png",
      "liga": "Brasileirão Serie B",
      "liga_corta": "Brasileirão Serie B",
      "liga_slug": "bra.2",
      "prioridad_liga": 112,
      "competicion": {
        "nombre": "Brasileirão Serie B",
        "nombre_corto": "Brasileirão Serie B",
        "slug": "bra.2",
        "prioridad": 112
      },
      "fecha": "2026-05-04",
      "hora_inicio": "19:00",
      "hora": "38'",
      "mostrar_tiempo": "38'",
      "estado": "First Half",
      "estado_corto": "38'",
      "estado_nombre": "STATUS_FIRST_HALF",
      "completado": false,
      "minuto": "38'",
      "periodo": 1,
      "marcador_local": "0",
      "marcador_visitante": "0",
      "resultado": "0-0",
      "mostrar_marcador": true,
      "goleadores": [],
      "fecha_espn": "2026-05-04T22:00Z",
      "url_espn": "https://www.espn.com.ar/futbol/partido/_/juegoId/401860124/athletic-vila-nova"
    },
    {
      "id": "762895",
      "partido": "Gimnasia (Mendoza) vs Defensa y Justicia",
      "local": "Gimnasia (Mendoza)",
      "visitante": "Defensa y Justicia",
      "local_id": "11972",
      "visitante_id": "8950",
      "local_logo": "https://a.espncdn.com/i/teamlogos/soccer/500/11972.png",
      "visitante_logo": "https://a.espncdn.com/i/teamlogos/soccer/500/8950.png",
      "liga": "Liga Profesional Argentina",
      "liga_corta": "Liga Profesional Argentina",
      "liga_slug": "arg.1",
      "prioridad_liga": 120,
      "competicion": {
        "nombre": "Liga Profesional Argentina",
        "nombre_corto": "Liga Profesional Argentina",
        "slug": "arg.1",
        "prioridad": 120
      },
      "fecha": "2026-05-04",
      "hora_inicio": "17:00",
      "hora": "Fin",
      "mostrar_tiempo": "Fin",
      "estado": "Tiempo Completo",
      "estado_corto": "F",
      "estado_nombre": "STATUS_FULL_TIME",
      "completado": true,
      "minuto": null,
      "periodo": null,
      "marcador_local": "2",
      "marcador_visitante": "1",
      "resultado": "2-1",
      "mostrar_marcador": true,
      "goleadores": [],
      "fecha_espn": "2026-05-04T20:00Z",
      "url_espn": "https://www.espn.com.ar/futbol/partido/_/juegoId/762895"
    },
    {
      "id": "762903",
      "partido": "Vélez Sarsfield vs Newell's Old Boys",
      "local": "Vélez Sarsfield",
      "visitante": "Newell's Old Boys",
      "local_id": "21",
      "visitante_id": "14",
      "local_logo": "https://a.espncdn.com/i/teamlogos/soccer/500/21.png",
      "visitante_logo": "https://a.espncdn.com/i/teamlogos/soccer/500/14.png",
      "liga": "Liga Profesional Argentina",
      "liga_corta": "Liga Profesional Argentina",
      "liga_slug": "arg.1",
      "prioridad_liga": 120,
      "competicion": {
        "nombre": "Liga Profesional Argentina",
        "nombre_corto": "Liga Profesional Argentina",
        "slug": "arg.1",
        "prioridad": 120
      },
      "fecha": "2026-05-04",
      "hora_inicio": "19:15",
      "hora": "19'",
      "mostrar_tiempo": "19'",
      "estado": "First Half",
      "estado_corto": "19'",
      "estado_nombre": "STATUS_FIRST_HALF",
      "completado": false,
      "minuto": "19'",
      "periodo": 1,
      "marcador_local": "0",
      "marcador_visitante": "0",
      "resultado": "0-0",
      "mostrar_marcador": true,
      "goleadores": [],
      "fecha_espn": "2026-05-04T22:15Z",
      "url_espn": "https://www.espn.com.ar/futbol/partido/_/juegoId/762903/newells-old-boys-velez-sarsfield"
    },
    {
      "id": "762908",
      "partido": "Estudiantes de Río Cuarto vs Instituto (Córdoba)",
      "local": "Estudiantes de Río Cuarto",
      "visitante": "Instituto (Córdoba)",
      "local_id": "19685",
      "visitante_id": "2975",
      "local_logo": "https://a.espncdn.com/i/teamlogos/soccer/500/19685.png",
      "visitante_logo": "https://a.espncdn.com/i/teamlogos/soccer/500/2975.png",
      "liga": "Liga Profesional Argentina",
      "liga_corta": "Liga Profesional Argentina",
      "liga_slug": "arg.1",
      "prioridad_liga": 120,
      "competicion": {
        "nombre": "Liga Profesional Argentina",
        "nombre_corto": "Liga Profesional Argentina",
        "slug": "arg.1",
        "prioridad": 120
      },
      "fecha": "2026-05-04",
      "hora_inicio": "21:30",
      "hora": "0'",
      "mostrar_tiempo": "0'",
      "estado": "Agendado",
      "estado_corto": "Scheduled",
      "estado_nombre": "STATUS_SCHEDULED",
      "completado": false,
      "minuto": "0'",
      "periodo": null,
      "marcador_local": null,
      "marcador_visitante": null,
      "resultado": null,
      "mostrar_marcador": false,
      "goleadores": [],
      "fecha_espn": "2026-05-05T00:30Z",
      "url_espn": "https://www.espn.com.ar/futbol/partido/_/juegoId/762908/instituto-cordoba-estudiantes-de-rio-cuarto"
    },
    {
      "id": "401843818",
      "partido": "Quilmes vs Chacarita Juniors",
      "local": "Quilmes",
      "visitante": "Chacarita Juniors",
      "local_id": "2741",
      "visitante_id": "6",
      "local_logo": "https://a.espncdn.com/i/teamlogos/soccer/500/2741.png",
      "visitante_logo": "https://a.espncdn.com/i/teamlogos/soccer/500/6.png",
      "liga": "Primera Nacional Argentina",
      "liga_corta": "Primera Nacional Argentina",
      "liga_slug": "arg.2",
      "prioridad_liga": 123,
      "competicion": {
        "nombre": "Primera Nacional Argentina",
        "nombre_corto": "Primera Nacional Argentina",
        "slug": "arg.2",
        "prioridad": 123
      },
      "fecha": "2026-05-04",
      "hora_inicio": "20:00",
      "hora": "0'",
      "mostrar_tiempo": "0'",
      "estado": "Agendado",
      "estado_corto": "Scheduled",
      "estado_nombre": "STATUS_SCHEDULED",
      "completado": false,
      "minuto": "0'",
      "periodo": null,
      "marcador_local": null,
      "marcador_visitante": null,
      "resultado": null,
      "mostrar_marcador": false,
      "goleadores": [],
      "fecha_espn": "2026-05-04T23:00Z",
      "url_espn": "https://www.espn.com.ar/futbol/partido/_/juegoId/401843818/chacarita-juniors-quilmes"
    },
    {
      "id": "401843813",
      "partido": "Gimnasia y Tiro (Salta) vs Agropecuario",
      "local": "Gimnasia y Tiro (Salta)",
      "visitante": "Agropecuario",
      "local_id": "10743",
      "visitante_id": "13913",
      "local_logo": "https://a.espncdn.com/i/teamlogos/soccer/500/10743.png",
      "visitante_logo": "https://a.espncdn.com/i/teamlogos/soccer/500/13913.png",
      "liga": "Primera Nacional Argentina",
      "liga_corta": "Primera Nacional Argentina",
      "liga_slug": "arg.2",
      "prioridad_liga": 123,
      "competicion": {
        "nombre": "Primera Nacional Argentina",
        "nombre_corto": "Primera Nacional Argentina",
        "slug": "arg.2",
        "prioridad": 123
      },
      "fecha": "2026-05-04",
      "hora_inicio": "21:30",
      "hora": "0'",
      "mostrar_tiempo": "0'",
      "estado": "Agendado",
      "estado_corto": "Scheduled",
      "estado_nombre": "STATUS_SCHEDULED",
      "completado": false,
      "minuto": "0'",
      "periodo": null,
      "marcador_local": null,
      "marcador_visitante": null,
      "resultado": null,
      "mostrar_marcador": false,
      "goleadores": [],
      "fecha_espn": "2026-05-05T00:30Z",
      "url_espn": "https://www.espn.com.ar/futbol/partido/_/juegoId/401843813/agropecuario-gimnasia-y-tiro-salta"
    },
    {
      "id": "401861858",
      "partido": "Peñarol vs Defensor Sporting",
      "local": "Peñarol",
      "visitante": "Defensor Sporting",
      "local_id": "2683",
      "visitante_id": "1007",
      "local_logo": "https://a.espncdn.com/i/teamlogos/soccer/500/2683.png",
      "visitante_logo": "https://a.espncdn.com/i/teamlogos/soccer/500/1007.png",
      "liga": "Primera División Uruguay",
      "liga_corta": "Primera División Uruguay",
      "liga_slug": "uru.1",
      "prioridad_liga": 130,
      "competicion": {
        "nombre": "Primera División Uruguay",
        "nombre_corto": "Primera División Uruguay",
        "slug": "uru.1",
        "prioridad": 130
      },
      "fecha": "2026-05-04",
      "hora_inicio": "19:30",
      "hora": "0'",
      "mostrar_tiempo": "0'",
      "estado": "Agendado",
      "estado_corto": "Scheduled",
      "estado_nombre": "STATUS_SCHEDULED",
      "completado": false,
      "minuto": "0'",
      "periodo": null,
      "marcador_local": null,
      "marcador_visitante": null,
      "resultado": null,
      "mostrar_marcador": false,
      "goleadores": [],
      "fecha_espn": "2026-05-04T22:30Z",
      "url_espn": "https://www.espn.com.ar/futbol/partido/_/juegoId/401861858/defensor-sporting-penarol"
    },
    {
      "id": "401857482",
      "partido": "Los Chankas vs Deportivo Garcilaso",
      "local": "Los Chankas",
      "visitante": "Deportivo Garcilaso",
      "local_id": "22168",
      "visitante_id": "21819",
      "local_logo": "https://a.espncdn.com/i/teamlogos/soccer/500/22168.png",
      "visitante_logo": "https://a.espncdn.com/i/teamlogos/soccer/500/21819.png",
      "liga": "Liga 1 Perú",
      "liga_corta": "Liga 1 Perú",
      "liga_slug": "per.1",
      "prioridad_liga": 134,
      "competicion": {
        "nombre": "Liga 1 Perú",
        "nombre_corto": "Liga 1 Perú",
        "slug": "per.1",
        "prioridad": 134
      },
      "fecha": "2026-05-04",
      "hora_inicio": "15:00",
      "hora": "Fin",
      "mostrar_tiempo": "Fin",
      "estado": "Tiempo Completo",
      "estado_corto": "F",
      "estado_nombre": "STATUS_FULL_TIME",
      "completado": true,
      "minuto": null,
      "periodo": null,
      "marcador_local": "0",
      "marcador_visitante": "1",
      "resultado": "0-1",
      "mostrar_marcador": true,
      "goleadores": [],
      "fecha_espn": "2026-05-04T18:00Z",
      "url_espn": "https://www.espn.com.ar/futbol/partido/_/juegoId/401857482/deportivo-garcilaso-los-chankas"
    },
    {
      "id": "401866921",
      "partido": "Universitario de Vinto vs Blooming",
      "local": "Universitario de Vinto",
      "visitante": "Blooming",
      "local_id": "21379",
      "visitante_id": "6047",
      "local_logo": "https://a.espncdn.com/i/teamlogos/soccer/500/21379.png",
      "visitante_logo": "https://a.espncdn.com/i/teamlogos/soccer/500/6047.png",
      "liga": "Primera División Bolivia",
      "liga_corta": "Primera División Bolivia",
      "liga_slug": "bol.1",
      "prioridad_liga": 136,
      "competicion": {
        "nombre": "Primera División Bolivia",
        "nombre_corto": "Primera División Bolivia",
        "slug": "bol.1",
        "prioridad": 136
      },
      "fecha": "2026-05-04",
      "hora_inicio": "21:00",
      "hora": "0'",
      "mostrar_tiempo": "0'",
      "estado": "Agendado",
      "estado_corto": "Scheduled",
      "estado_nombre": "STATUS_SCHEDULED",
      "completado": false,
      "minuto": "0'",
      "periodo": null,
      "marcador_local": null,
      "marcador_visitante": null,
      "resultado": null,
      "mostrar_marcador": false,
      "goleadores": [],
      "fecha_espn": "2026-05-05T00:00Z",
      "url_espn": "https://www.espn.com.ar/futbol/partido/_/juegoId/401866921/blooming-universitario-de-vinto"
    },
    {
      "id": "756177",
      "partido": "Al Fayha vs Al Riyadh",
      "local": "Al Fayha",
      "visitante": "Al Riyadh",
      "local_id": "21827",
      "visitante_id": "21965",
      "local_logo": "https://a.espncdn.com/i/teamlogos/soccer/500/21827.png",
      "visitante_logo": "https://a.espncdn.com/i/teamlogos/soccer/500/21965.png",
      "liga": "Saudi Pro League",
      "liga_corta": "Saudi Pro League",
      "liga_slug": "ksa.1",
      "prioridad_liga": 310,
      "competicion": {
        "nombre": "Saudi Pro League",
        "nombre_corto": "Saudi Pro League",
        "slug": "ksa.1",
        "prioridad": 310
      },
      "fecha": "2026-05-04",
      "hora_inicio": "13:10",
      "hora": "Fin",
      "mostrar_tiempo": "Fin",
      "estado": "Tiempo Completo",
      "estado_corto": "F",
      "estado_nombre": "STATUS_FULL_TIME",
      "completado": true,
      "minuto": null,
      "periodo": null,
      "marcador_local": "4",
      "marcador_visitante": "2",
      "resultado": "4-2",
      "mostrar_marcador": true,
      "goleadores": [],
      "fecha_espn": "2026-05-04T16:10Z",
      "url_espn": "https://www.espn.com.ar/futbol/partido/_/juegoId/756177/al-riyadh-al-fayha"
    },
    {
      "id": "756174",
      "partido": "Al Ettifaq vs Al Najma",
      "local": "Al Ettifaq",
      "visitante": "Al Najma",
      "local_id": "8363",
      "visitante_id": "22023",
      "local_logo": "https://a.espncdn.com/i/teamlogos/soccer/500/8363.png",
      "visitante_logo": "https://a.espncdn.com/i/teamlogos/soccer/500/22023.png",
      "liga": "Saudi Pro League",
      "liga_corta": "Saudi Pro League",
      "liga_slug": "ksa.1",
      "prioridad_liga": 310,
      "competicion": {
        "nombre": "Saudi Pro League",
        "nombre_corto": "Saudi Pro League",
        "slug": "ksa.1",
        "prioridad": 310
      },
      "fecha": "2026-05-04",
      "hora_inicio": "15:00",
      "hora": "Fin",
      "mostrar_tiempo": "Fin",
      "estado": "Tiempo Completo",
      "estado_corto": "F",
      "estado_nombre": "STATUS_FULL_TIME",
      "completado": true,
      "minuto": null,
      "periodo": null,
      "marcador_local": "0",
      "marcador_visitante": "0",
      "resultado": "0-0",
      "mostrar_marcador": true,
      "goleadores": [],
      "fecha_espn": "2026-05-04T18:00Z",
      "url_espn": "https://www.espn.com.ar/futbol/partido/_/juegoId/756174/al-najma-al-ettifaq"
    },
    {
      "id": "756179",
      "partido": "Al Ittihad vs Al Kholood",
      "local": "Al Ittihad",
      "visitante": "Al Kholood",
      "local_id": "2276",
      "visitante_id": "22028",
      "local_logo": "https://a.espncdn.com/i/teamlogos/soccer/500/2276.png",
      "visitante_logo": "https://a.espncdn.com/i/teamlogos/soccer/500/22028.png",
      "liga": "Saudi Pro League",
      "liga_corta": "Saudi Pro League",
      "liga_slug": "ksa.1",
      "prioridad_liga": 310,
      "competicion": {
        "nombre": "Saudi Pro League",
        "nombre_corto": "Saudi Pro League",
        "slug": "ksa.1",
        "prioridad": 310
      },
      "fecha": "2026-05-04",
      "hora_inicio": "15:00",
      "hora": "Fin",
      "mostrar_tiempo": "Fin",
      "estado": "Tiempo Completo",
      "estado_corto": "F",
      "estado_nombre": "STATUS_FULL_TIME",
      "completado": true,
      "minuto": null,
      "periodo": null,
      "marcador_local": "0",
      "marcador_visitante": "0",
      "resultado": "0-0",
      "mostrar_marcador": true,
      "goleadores": [],
      "fecha_espn": "2026-05-04T18:00Z",
      "url_espn": "https://www.espn.com.ar/futbol/partido/_/juegoId/756179/al-kholood-al-ittihad"
    },
    {
      "id": "754418",
      "partido": "Aston Villa vs West Ham United",
      "local": "Aston Villa",
      "visitante": "West Ham United",
      "local_id": "20707",
      "visitante_id": "19975",
      "local_logo": "https://a.espncdn.com/i/teamlogos/soccer/500/20707.png",
      "visitante_logo": "https://a.espncdn.com/i/teamlogos/soccer/500/19975.png",
      "liga": "Women's Super League Inglaterra",
      "liga_corta": "Women's Super League Inglaterra",
      "liga_slug": "eng.w.1",
      "prioridad_liga": 503,
      "competicion": {
        "nombre": "Women's Super League Inglaterra",
        "nombre_corto": "Women's Super League Inglaterra",
        "slug": "eng.w.1",
        "prioridad": 503
      },
      "fecha": "2026-05-04",
      "hora_inicio": "09:00",
      "hora": "Fin",
      "mostrar_tiempo": "Fin",
      "estado": "Tiempo Completo",
      "estado_corto": "F",
      "estado_nombre": "STATUS_FULL_TIME",
      "completado": true,
      "minuto": null,
      "periodo": null,
      "marcador_local": "0",
      "marcador_visitante": "2",
      "resultado": "0-2",
      "mostrar_marcador": true,
      "goleadores": [],
      "fecha_espn": "2026-05-04T12:00Z",
      "url_espn": "https://www.espn.com.ar/futbol/partido/_/juegoId/754418/west-ham-united-aston-villa"
    },
    {
      "id": "401860516",
      "partido": "Odisha FC vs Bengaluru FC",
      "local": "Odisha FC",
      "visitante": "Bengaluru FC",
      "local_id": "17998",
      "visitante_id": "18851",
      "local_logo": "https://a.espncdn.com/i/teamlogos/soccer/500/17998.png",
      "visitante_logo": "https://a.espncdn.com/i/teamlogos/soccer/500/18851.png",
      "liga": "Indian Super League",
      "liga_corta": "Indian Super League",
      "liga_slug": "ind.1",
      "prioridad_liga": 9999,
      "competicion": {
        "nombre": "Indian Super League",
        "nombre_corto": "Indian Super League",
        "slug": "ind.1",
        "prioridad": 9999
      },
      "fecha": "2026-05-04",
      "hora_inicio": "11:00",
      "hora": "Fin",
      "mostrar_tiempo": "Fin",
      "estado": "Tiempo Completo",
      "estado_corto": "F",
      "estado_nombre": "STATUS_FULL_TIME",
      "completado": true,
      "minuto": null,
      "periodo": null,
      "marcador_local": "1",
      "marcador_visitante": "1",
      "resultado": "1-1",
      "mostrar_marcador": true,
      "goleadores": [],
      "fecha_espn": "2026-05-04T14:00Z",
      "url_espn": "https://www.espn.com.ar/futbol/partido/_/juegoId/401860516/bengaluru-fc-odisha-fc"
    },
    {
      "id": "763106",
      "partido": "Bohemians vs Shelbourne",
      "local": "Bohemians",
      "visitante": "Shelbourne",
      "local_id": "615",
      "visitante_id": "20297",
      "local_logo": "https://a.espncdn.com/i/teamlogos/soccer/500/615.png",
      "visitante_logo": "https://a.espncdn.com/i/teamlogos/soccer/500/20297.png",
      "liga": "Premier Division Irlanda",
      "liga_corta": "Premier Division Irlanda",
      "liga_slug": "irl.1",
      "prioridad_liga": 9999,
      "competicion": {
        "nombre": "Premier Division Irlanda",
        "nombre_corto": "Premier Division Irlanda",
        "slug": "irl.1",
        "prioridad": 9999
      },
      "fecha": "2026-05-04",
      "hora_inicio": "13:00",
      "hora": "Fin",
      "mostrar_tiempo": "Fin",
      "estado": "Tiempo Completo",
      "estado_corto": "F",
      "estado_nombre": "STATUS_FULL_TIME",
      "completado": true,
      "minuto": null,
      "periodo": null,
      "marcador_local": "2",
      "marcador_visitante": "2",
      "resultado": "2-2",
      "mostrar_marcador": true,
      "goleadores": [],
      "fecha_espn": "2026-05-04T16:00Z",
      "url_espn": "https://www.espn.com.ar/futbol/partido/_/juegoId/763106/shelbourne-bohemians"
    },
    {
      "id": "763105",
      "partido": "Derry City vs Galway Utd",
      "local": "Derry City",
      "visitante": "Galway Utd",
      "local_id": "2712",
      "visitante_id": "7587",
      "local_logo": "https://a.espncdn.com/i/teamlogos/soccer/500/2712.png",
      "visitante_logo": "https://a.espncdn.com/i/teamlogos/soccer/500/7587.png",
      "liga": "Premier Division Irlanda",
      "liga_corta": "Premier Division Irlanda",
      "liga_slug": "irl.1",
      "prioridad_liga": 9999,
      "competicion": {
        "nombre": "Premier Division Irlanda",
        "nombre_corto": "Premier Division Irlanda",
        "slug": "irl.1",
        "prioridad": 9999
      },
      "fecha": "2026-05-04",
      "hora_inicio": "13:00",
      "hora": "Fin",
      "mostrar_tiempo": "Fin",
      "estado": "Tiempo Completo",
      "estado_corto": "F",
      "estado_nombre": "STATUS_FULL_TIME",
      "completado": true,
      "minuto": null,
      "periodo": null,
      "marcador_local": "1",
      "marcador_visitante": "1",
      "resultado": "1-1",
      "mostrar_marcador": true,
      "goleadores": [],
      "fecha_espn": "2026-05-04T16:00Z",
      "url_espn": "https://www.espn.com.ar/futbol/partido/_/juegoId/763105/galway-utd-derry-city"
    },
    {
      "id": "763107",
      "partido": "Shamrock Rovers vs Drogheda Utd",
      "local": "Shamrock Rovers",
      "visitante": "Drogheda Utd",
      "local_id": "2564",
      "visitante_id": "6741",
      "local_logo": "https://a.espncdn.com/i/teamlogos/soccer/500/2564.png",
      "visitante_logo": "https://a.espncdn.com/i/teamlogos/soccer/500/6741.png",
      "liga": "Premier Division Irlanda",
      "liga_corta": "Premier Division Irlanda",
      "liga_slug": "irl.1",
      "prioridad_liga": 9999,
      "competicion": {
        "nombre": "Premier Division Irlanda",
        "nombre_corto": "Premier Division Irlanda",
        "slug": "irl.1",
        "prioridad": 9999
      },
      "fecha": "2026-05-04",
      "hora_inicio": "13:00",
      "hora": "Fin",
      "mostrar_tiempo": "Fin",
      "estado": "Tiempo Completo",
      "estado_corto": "F",
      "estado_nombre": "STATUS_FULL_TIME",
      "completado": true,
      "minuto": null,
      "periodo": null,
      "marcador_local": "4",
      "marcador_visitante": "1",
      "resultado": "4-1",
      "mostrar_marcador": true,
      "goleadores": [],
      "fecha_espn": "2026-05-04T16:00Z",
      "url_espn": "https://www.espn.com.ar/futbol/partido/_/juegoId/763107/drogheda-utd-shamrock-rovers"
    },
    {
      "id": "763109",
      "partido": "Sligo vs St Patricks Athletic",
      "local": "Sligo",
      "visitante": "St Patricks Athletic",
      "local_id": "7601",
      "visitante_id": "7588",
      "local_logo": "https://a.espncdn.com/i/teamlogos/soccer/500/7601.png",
      "visitante_logo": "https://a.espncdn.com/i/teamlogos/soccer/500/7588.png",
      "liga": "Premier Division Irlanda",
      "liga_corta": "Premier Division Irlanda",
      "liga_slug": "irl.1",
      "prioridad_liga": 9999,
      "competicion": {
        "nombre": "Premier Division Irlanda",
        "nombre_corto": "Premier Division Irlanda",
        "slug": "irl.1",
        "prioridad": 9999
      },
      "fecha": "2026-05-04",
      "hora_inicio": "13:00",
      "hora": "Fin",
      "mostrar_tiempo": "Fin",
      "estado": "Tiempo Completo",
      "estado_corto": "F",
      "estado_nombre": "STATUS_FULL_TIME",
      "completado": true,
      "minuto": null,
      "periodo": null,
      "marcador_local": "1",
      "marcador_visitante": "1",
      "resultado": "1-1",
      "mostrar_marcador": true,
      "goleadores": [],
      "fecha_espn": "2026-05-04T16:00Z",
      "url_espn": "https://www.espn.com.ar/futbol/partido/_/juegoId/763109/st-patricks-athletic-sligo"
    },
    {
      "id": "763108",
      "partido": "Waterford vs Dundalk",
      "local": "Waterford",
      "visitante": "Dundalk",
      "local_id": "18968",
      "visitante_id": "2559",
      "local_logo": "https://a.espncdn.com/i/teamlogos/soccer/500/18968.png",
      "visitante_logo": "https://a.espncdn.com/i/teamlogos/soccer/500/2559.png",
      "liga": "Premier Division Irlanda",
      "liga_corta": "Premier Division Irlanda",
      "liga_slug": "irl.1",
      "prioridad_liga": 9999,
      "competicion": {
        "nombre": "Premier Division Irlanda",
        "nombre_corto": "Premier Division Irlanda",
        "slug": "irl.1",
        "prioridad": 9999
      },
      "fecha": "2026-05-04",
      "hora_inicio": "13:00",
      "hora": "Fin",
      "mostrar_tiempo": "Fin",
      "estado": "Tiempo Completo",
      "estado_corto": "F",
      "estado_nombre": "STATUS_FULL_TIME",
      "completado": true,
      "minuto": null,
      "periodo": null,
      "marcador_local": "3",
      "marcador_visitante": "3",
      "resultado": "3-3",
      "mostrar_marcador": true,
      "goleadores": [],
      "fecha_espn": "2026-05-04T16:00Z",
      "url_espn": "https://www.espn.com.ar/futbol/partido/_/juegoId/763108/dundalk-waterford"
    },
    {
      "id": "401843333",
      "partido": "Bodo/Glimt vs Molde",
      "local": "Bodo/Glimt",
      "visitante": "Molde",
      "local_id": "2980",
      "visitante_id": "2715",
      "local_logo": "https://a.espncdn.com/i/teamlogos/soccer/500/2980.png",
      "visitante_logo": "https://a.espncdn.com/i/teamlogos/soccer/500/2715.png",
      "liga": "Eliteserien Noruega",
      "liga_corta": "Eliteserien Noruega",
      "liga_slug": "nor.1",
      "prioridad_liga": 9999,
      "competicion": {
        "nombre": "Eliteserien Noruega",
        "nombre_corto": "Eliteserien Noruega",
        "slug": "nor.1",
        "prioridad": 9999
      },
      "fecha": "2026-05-04",
      "hora_inicio": "14:00",
      "hora": "Fin",
      "mostrar_tiempo": "Fin",
      "estado": "Tiempo Completo",
      "estado_corto": "F",
      "estado_nombre": "STATUS_FULL_TIME",
      "completado": true,
      "minuto": null,
      "periodo": null,
      "marcador_local": "0",
      "marcador_visitante": "1",
      "resultado": "0-1",
      "mostrar_marcador": true,
      "goleadores": [],
      "fecha_espn": "2026-05-04T17:00Z",
      "url_espn": "https://www.espn.com.ar/futbol/partido/_/juegoId/401843333"
    },
    {
      "id": "401842699",
      "partido": "Djurgården vs IFK Göteborg",
      "local": "Djurgården",
      "visitante": "IFK Göteborg",
      "local_id": "2339",
      "visitante_id": "2556",
      "local_logo": "https://a.espncdn.com/i/teamlogos/soccer/500/2339.png",
      "visitante_logo": "https://a.espncdn.com/i/teamlogos/soccer/500/2556.png",
      "liga": "Allsvenskan Suecia",
      "liga_corta": "Allsvenskan Suecia",
      "liga_slug": "swe.1",
      "prioridad_liga": 9999,
      "competicion": {
        "nombre": "Allsvenskan Suecia",
        "nombre_corto": "Allsvenskan Suecia",
        "slug": "swe.1",
        "prioridad": 9999
      },
      "fecha": "2026-05-04",
      "hora_inicio": "14:00",
      "hora": "Fin",
      "mostrar_tiempo": "Fin",
      "estado": "Tiempo Completo",
      "estado_corto": "F",
      "estado_nombre": "STATUS_FULL_TIME",
      "completado": true,
      "minuto": null,
      "periodo": null,
      "marcador_local": "6",
      "marcador_visitante": "0",
      "resultado": "6-0",
      "mostrar_marcador": true,
      "goleadores": [],
      "fecha_espn": "2026-05-04T17:00Z",
      "url_espn": "https://www.espn.com.ar/futbol/partido/_/juegoId/401842699/ifk-goteborg-djurgarden"
    },
    {
      "id": "401863674",
      "partido": "FC Midtjylland vs Viborg FF",
      "local": "FC Midtjylland",
      "visitante": "Viborg FF",
      "local_id": "572",
      "visitante_id": "3153",
      "local_logo": "https://a.espncdn.com/i/teamlogos/soccer/500/572.png",
      "visitante_logo": "https://a.espncdn.com/i/teamlogos/soccer/500/3153.png",
      "liga": "Superliga Dinamarca",
      "liga_corta": "Superliga Dinamarca",
      "liga_slug": "den.1",
      "prioridad_liga": 9999,
      "competicion": {
        "nombre": "Superliga Dinamarca",
        "nombre_corto": "Superliga Dinamarca",
        "slug": "den.1",
        "prioridad": 9999
      },
      "fecha": "2026-05-04",
      "hora_inicio": "14:00",
      "hora": "Fin",
      "mostrar_tiempo": "Fin",
      "estado": "Tiempo Completo",
      "estado_corto": "F",
      "estado_nombre": "STATUS_FULL_TIME",
      "completado": true,
      "minuto": null,
      "periodo": null,
      "marcador_local": "3",
      "marcador_visitante": "3",
      "resultado": "3-3",
      "mostrar_marcador": true,
      "goleadores": [],
      "fecha_espn": "2026-05-04T17:00Z",
      "url_espn": "https://www.espn.com.ar/futbol/partido/_/juegoId/401863674"
    },
    {
      "id": "401842703",
      "partido": "Halmstads BK vs IF Brommapojkarna",
      "local": "Halmstads BK",
      "visitante": "IF Brommapojkarna",
      "local_id": "3017",
      "visitante_id": "8221",
      "local_logo": "https://a.espncdn.com/i/teamlogos/soccer/500/3017.png",
      "visitante_logo": "https://a.espncdn.com/i/teamlogos/soccer/500/8221.png",
      "liga": "Allsvenskan Suecia",
      "liga_corta": "Allsvenskan Suecia",
      "liga_slug": "swe.1",
      "prioridad_liga": 9999,
      "competicion": {
        "nombre": "Allsvenskan Suecia",
        "nombre_corto": "Allsvenskan Suecia",
        "slug": "swe.1",
        "prioridad": 9999
      },
      "fecha": "2026-05-04",
      "hora_inicio": "14:00",
      "hora": "Fin",
      "mostrar_tiempo": "Fin",
      "estado": "Tiempo Completo",
      "estado_corto": "F",
      "estado_nombre": "STATUS_FULL_TIME",
      "completado": true,
      "minuto": null,
      "periodo": null,
      "marcador_local": "1",
      "marcador_visitante": "3",
      "resultado": "1-3",
      "mostrar_marcador": true,
      "goleadores": [],
      "fecha_espn": "2026-05-04T17:00Z",
      "url_espn": "https://www.espn.com.ar/futbol/partido/_/juegoId/401842703/if-brommapojkarna-halmstads-bk"
    }
  ],
  "agrupado_por_liga": [
    {
      "liga": "Premier League",
      "liga_slug": "eng.1",
      "prioridad": 20,
      "total": 2,
      "partidos": [
        {
          "id": "740940",
          "partido": "Chelsea vs Nottingham Forest",
          "local": "Chelsea",
          "visitante": "Nottingham Forest",
          "local_id": "363",
          "visitante_id": "393",
          "local_logo": "https://a.espncdn.com/i/teamlogos/soccer/500/363.png",
          "visitante_logo": "https://a.espncdn.com/i/teamlogos/soccer/500/393.png",
          "liga": "Premier League",
          "liga_corta": "Premier League",
          "liga_slug": "eng.1",
          "prioridad_liga": 20,
          "competicion": {
            "nombre": "Premier League",
            "nombre_corto": "Premier League",
            "slug": "eng.1",
            "prioridad": 20
          },
          "fecha": "2026-05-04",
          "hora_inicio": "11:00",
          "hora": "Fin",
          "mostrar_tiempo": "Fin",
          "estado": "Tiempo Completo",
          "estado_corto": "F",
          "estado_nombre": "STATUS_FULL_TIME",
          "completado": true,
          "minuto": null,
          "periodo": null,
          "marcador_local": "1",
          "marcador_visitante": "3",
          "resultado": "1-3",
          "mostrar_marcador": true,
          "goleadores": [],
          "fecha_espn": "2026-05-04T14:00Z",
          "url_espn": "https://www.espn.com.ar/futbol/partido/_/juegoId/740940/nottingham-forest-chelsea"
        },
        {
          "id": "740941",
          "partido": "Everton vs Manchester City",
          "local": "Everton",
          "visitante": "Manchester City",
          "local_id": "368",
          "visitante_id": "382",
          "local_logo": "https://a.espncdn.com/i/teamlogos/soccer/500/368.png",
          "visitante_logo": "https://a.espncdn.com/i/teamlogos/soccer/500/382.png",
          "liga": "Premier League",
          "liga_corta": "Premier League",
          "liga_slug": "eng.1",
          "prioridad_liga": 20,
          "competicion": {
            "nombre": "Premier League",
            "nombre_corto": "Premier League",
            "slug": "eng.1",
            "prioridad": 20
          },
          "fecha": "2026-05-04",
          "hora_inicio": "16:00",
          "hora": "Fin",
          "mostrar_tiempo": "Fin",
          "estado": "Tiempo Completo",
          "estado_corto": "F",
          "estado_nombre": "STATUS_FULL_TIME",
          "completado": true,
          "minuto": null,
          "periodo": null,
          "marcador_local": "3",
          "marcador_visitante": "3",
          "resultado": "3-3",
          "mostrar_marcador": true,
          "goleadores": [],
          "fecha_espn": "2026-05-04T19:00Z",
          "url_espn": "https://www.espn.com.ar/futbol/partido/_/juegoId/740941/manchester-city-everton"
        }
      ]
    },
    {
      "liga": "LaLiga",
      "liga_slug": "esp.1",
      "prioridad": 21,
      "total": 1,
      "partidos": [
        {
          "id": "748478",
          "partido": "Sevilla FC vs Real Sociedad",
          "local": "Sevilla FC",
          "visitante": "Real Sociedad",
          "local_id": "243",
          "visitante_id": "89",
          "local_logo": "https://a.espncdn.com/i/teamlogos/soccer/500/243.png",
          "visitante_logo": "https://a.espncdn.com/i/teamlogos/soccer/500/89.png",
          "liga": "LaLiga",
          "liga_corta": "LaLiga",
          "liga_slug": "esp.1",
          "prioridad_liga": 21,
          "competicion": {
            "nombre": "LaLiga",
            "nombre_corto": "LaLiga",
            "slug": "esp.1",
            "prioridad": 21
          },
          "fecha": "2026-05-04",
          "hora_inicio": "16:00",
          "hora": "Fin",
          "mostrar_tiempo": "Fin",
          "estado": "Tiempo Completo",
          "estado_corto": "F",
          "estado_nombre": "STATUS_FULL_TIME",
          "completado": true,
          "minuto": null,
          "periodo": null,
          "marcador_local": "1",
          "marcador_visitante": "0",
          "resultado": "1-0",
          "mostrar_marcador": true,
          "goleadores": [],
          "fecha_espn": "2026-05-04T19:00Z",
          "url_espn": "https://www.espn.com.ar/futbol/partido/_/juegoId/748478/real-sociedad-sevilla"
        }
      ]
    },
    {
      "liga": "Serie A",
      "liga_slug": "ita.1",
      "prioridad": 22,
      "total": 2,
      "partidos": [
        {
          "id": "737129",
          "partido": "Cremonese vs Lazio",
          "local": "Cremonese",
          "visitante": "Lazio",
          "local_id": "4050",
          "visitante_id": "112",
          "local_logo": "https://a.espncdn.com/i/teamlogos/soccer/500/4050.png",
          "visitante_logo": "https://a.espncdn.com/i/teamlogos/soccer/500/112.png",
          "liga": "Serie A",
          "liga_corta": "Serie A",
          "liga_slug": "ita.1",
          "prioridad_liga": 22,
          "competicion": {
            "nombre": "Serie A",
            "nombre_corto": "Serie A",
            "slug": "ita.1",
            "prioridad": 22
          },
          "fecha": "2026-05-04",
          "hora_inicio": "13:30",
          "hora": "Fin",
          "mostrar_tiempo": "Fin",
          "estado": "Tiempo Completo",
          "estado_corto": "F",
          "estado_nombre": "STATUS_FULL_TIME",
          "completado": true,
          "minuto": null,
          "periodo": null,
          "marcador_local": "1",
          "marcador_visitante": "2",
          "resultado": "1-2",
          "mostrar_marcador": true,
          "goleadores": [],
          "fecha_espn": "2026-05-04T16:30Z",
          "url_espn": "https://www.espn.com.ar/futbol/partido/_/juegoId/737129/lazio-cremonese"
        },
        {
          "id": "737125",
          "partido": "AS Roma vs Fiorentina",
          "local": "AS Roma",
          "visitante": "Fiorentina",
          "local_id": "104",
          "visitante_id": "109",
          "local_logo": "https://a.espncdn.com/i/teamlogos/soccer/500/104.png",
          "visitante_logo": "https://a.espncdn.com/i/teamlogos/soccer/500/109.png",
          "liga": "Serie A",
          "liga_corta": "Serie A",
          "liga_slug": "ita.1",
          "prioridad_liga": 22,
          "competicion": {
            "nombre": "Serie A",
            "nombre_corto": "Serie A",
            "slug": "ita.1",
            "prioridad": 22
          },
          "fecha": "2026-05-04",
          "hora_inicio": "15:45",
          "hora": "Fin",
          "mostrar_tiempo": "Fin",
          "estado": "Tiempo Completo",
          "estado_corto": "F",
          "estado_nombre": "STATUS_FULL_TIME",
          "completado": true,
          "minuto": null,
          "periodo": null,
          "marcador_local": "4",
          "marcador_visitante": "0",
          "resultado": "4-0",
          "mostrar_marcador": true,
          "goleadores": [],
          "fecha_espn": "2026-05-04T18:45Z",
          "url_espn": "https://www.espn.com.ar/futbol/partido/_/juegoId/737125/fiorentina-as-roma"
        }
      ]
    },
    {
      "liga": "LaLiga 2",
      "liga_slug": "esp.2",
      "prioridad": 36,
      "total": 1,
      "partidos": [
        {
          "id": "748933",
          "partido": "Almería vs Mirandés",
          "local": "Almería",
          "visitante": "Mirandés",
          "local_id": "6832",
          "visitante_id": "4515",
          "local_logo": "https://a.espncdn.com/i/teamlogos/soccer/500/6832.png",
          "visitante_logo": "https://a.espncdn.com/i/teamlogos/soccer/500/4515.png",
          "liga": "LaLiga 2",
          "liga_corta": "LaLiga 2",
          "liga_slug": "esp.2",
          "prioridad_liga": 36,
          "competicion": {
            "nombre": "LaLiga 2",
            "nombre_corto": "LaLiga 2",
            "slug": "esp.2",
            "prioridad": 36
          },
          "fecha": "2026-05-04",
          "hora_inicio": "15:30",
          "hora": "Fin",
          "mostrar_tiempo": "Fin",
          "estado": "Tiempo Completo",
          "estado_corto": "F",
          "estado_nombre": "STATUS_FULL_TIME",
          "completado": true,
          "minuto": null,
          "periodo": null,
          "marcador_local": "4",
          "marcador_visitante": "2",
          "resultado": "4-2",
          "mostrar_marcador": true,
          "goleadores": [],
          "fecha_espn": "2026-05-04T18:30Z",
          "url_espn": "https://www.espn.com.ar/futbol/partido/_/juegoId/748933/mirandes-almeria"
        }
      ]
    },
    {
      "liga": "Primeira Liga",
      "liga_slug": "por.1",
      "prioridad": 50,
      "total": 1,
      "partidos": [
        {
          "id": "750530",
          "partido": "Sporting CP vs Vitória de Guimaraes",
          "local": "Sporting CP",
          "visitante": "Vitória de Guimaraes",
          "local_id": "2250",
          "visitante_id": "5309",
          "local_logo": "https://a.espncdn.com/i/teamlogos/soccer/500/2250.png",
          "visitante_logo": "https://a.espncdn.com/i/teamlogos/soccer/500/5309.png",
          "liga": "Primeira Liga",
          "liga_corta": "Primeira Liga",
          "liga_slug": "por.1",
          "prioridad_liga": 50,
          "competicion": {
            "nombre": "Primeira Liga",
            "nombre_corto": "Primeira Liga",
            "slug": "por.1",
            "prioridad": 50
          },
          "fecha": "2026-05-04",
          "hora_inicio": "16:15",
          "hora": "Fin",
          "mostrar_tiempo": "Fin",
          "estado": "Tiempo Completo",
          "estado_corto": "F",
          "estado_nombre": "STATUS_FULL_TIME",
          "completado": true,
          "minuto": null,
          "periodo": null,
          "marcador_local": "5",
          "marcador_visitante": "1",
          "resultado": "5-1",
          "mostrar_marcador": true,
          "goleadores": [],
          "fecha_espn": "2026-05-04T19:15Z",
          "url_espn": "https://www.espn.com.ar/futbol/partido/_/juegoId/750530/vitoria-de-guimaraes-sporting-cp"
        }
      ]
    },
    {
      "liga": "Scottish Premiership",
      "liga_slug": "sco.1",
      "prioridad": 54,
      "total": 1,
      "partidos": [
        {
          "id": "401867706",
          "partido": "Heart of Midlothian vs Rangers",
          "local": "Heart of Midlothian",
          "visitante": "Rangers",
          "local_id": "262",
          "visitante_id": "257",
          "local_logo": "https://a.espncdn.com/i/teamlogos/soccer/500/262.png",
          "visitante_logo": "https://a.espncdn.com/i/teamlogos/soccer/500/257.png",
          "liga": "Scottish Premiership",
          "liga_corta": "Scottish Premiership",
          "liga_slug": "sco.1",
          "prioridad_liga": 54,
          "competicion": {
            "nombre": "Scottish Premiership",
            "nombre_corto": "Scottish Premiership",
            "slug": "sco.1",
            "prioridad": 54
          },
          "fecha": "2026-05-04",
          "hora_inicio": "13:30",
          "hora": "Fin",
          "mostrar_tiempo": "Fin",
          "estado": "Tiempo Completo",
          "estado_corto": "F",
          "estado_nombre": "STATUS_FULL_TIME",
          "completado": true,
          "minuto": null,
          "periodo": null,
          "marcador_local": "2",
          "marcador_visitante": "1",
          "resultado": "2-1",
          "mostrar_marcador": true,
          "goleadores": [],
          "fecha_espn": "2026-05-04T16:30Z",
          "url_espn": "https://www.espn.com.ar/futbol/partido/_/juegoId/401867706/rangers-heart-of-midlothian"
        }
      ]
    },
    {
      "liga": "Austrian Bundesliga",
      "liga_slug": "aut.1",
      "prioridad": 55,
      "total": 2,
      "partidos": [
        {
          "id": "401864042",
          "partido": "SC Rheindorf Altach vs Wolfsberger",
          "local": "SC Rheindorf Altach",
          "visitante": "Wolfsberger",
          "local_id": "4405",
          "visitante_id": "13294",
          "local_logo": "https://a.espncdn.com/i/teamlogos/soccer/500/4405.png",
          "visitante_logo": "https://a.espncdn.com/i/teamlogos/soccer/500/13294.png",
          "liga": "Austrian Bundesliga",
          "liga_corta": "Austrian Bundesliga",
          "liga_slug": "aut.1",
          "prioridad_liga": 55,
          "competicion": {
            "nombre": "Austrian Bundesliga",
            "nombre_corto": "Austrian Bundesliga",
            "slug": "aut.1",
            "prioridad": 55
          },
          "fecha": "2026-05-04",
          "hora_inicio": "13:30",
          "hora": "Fin",
          "mostrar_tiempo": "Fin",
          "estado": "Tiempo Completo",
          "estado_corto": "F",
          "estado_nombre": "STATUS_FULL_TIME",
          "completado": true,
          "minuto": null,
          "periodo": null,
          "marcador_local": "1",
          "marcador_visitante": "4",
          "resultado": "1-4",
          "mostrar_marcador": true,
          "goleadores": [],
          "fecha_espn": "2026-05-04T16:30Z",
          "url_espn": "https://www.espn.com.ar/futbol/partido/_/juegoId/401864042/wolfsberger-sc-rheindorf-altach"
        },
        {
          "id": "401864040",
          "partido": "LASK Linz vs Rapid Vienna",
          "local": "LASK Linz",
          "visitante": "Rapid Vienna",
          "local_id": "4411",
          "visitante_id": "519",
          "local_logo": "https://a.espncdn.com/i/teamlogos/soccer/500/4411.png",
          "visitante_logo": "https://a.espncdn.com/i/teamlogos/soccer/500/519.png",
          "liga": "Austrian Bundesliga",
          "liga_corta": "Austrian Bundesliga",
          "liga_slug": "aut.1",
          "prioridad_liga": 55,
          "competicion": {
            "nombre": "Austrian Bundesliga",
            "nombre_corto": "Austrian Bundesliga",
            "slug": "aut.1",
            "prioridad": 55
          },
          "fecha": "2026-05-04",
          "hora_inicio": "15:30",
          "hora": "Fin",
          "mostrar_tiempo": "Fin",
          "estado": "Tiempo Completo",
          "estado_corto": "F",
          "estado_nombre": "STATUS_FULL_TIME",
          "completado": true,
          "minuto": null,
          "periodo": null,
          "marcador_local": "3",
          "marcador_visitante": "1",
          "resultado": "3-1",
          "mostrar_marcador": true,
          "goleadores": [],
          "fecha_espn": "2026-05-04T18:30Z",
          "url_espn": "https://www.espn.com.ar/futbol/partido/_/juegoId/401864040"
        }
      ]
    },
    {
      "liga": "Brasileirão Serie B",
      "liga_slug": "bra.2",
      "prioridad": 112,
      "total": 1,
      "partidos": [
        {
          "id": "401860124",
          "partido": "Vila Nova vs Athletic",
          "local": "Vila Nova",
          "visitante": "Athletic",
          "local_id": "9973",
          "visitante_id": "20851",
          "local_logo": "https://a.espncdn.com/i/teamlogos/soccer/500/9973.png",
          "visitante_logo": "https://a.espncdn.com/i/teamlogos/soccer/500/20851.png",
          "liga": "Brasileirão Serie B",
          "liga_corta": "Brasileirão Serie B",
          "liga_slug": "bra.2",
          "prioridad_liga": 112,
          "competicion": {
            "nombre": "Brasileirão Serie B",
            "nombre_corto": "Brasileirão Serie B",
            "slug": "bra.2",
            "prioridad": 112
          },
          "fecha": "2026-05-04",
          "hora_inicio": "19:00",
          "hora": "38'",
          "mostrar_tiempo": "38'",
          "estado": "First Half",
          "estado_corto": "38'",
          "estado_nombre": "STATUS_FIRST_HALF",
          "completado": false,
          "minuto": "38'",
          "periodo": 1,
          "marcador_local": "0",
          "marcador_visitante": "0",
          "resultado": "0-0",
          "mostrar_marcador": true,
          "goleadores": [],
          "fecha_espn": "2026-05-04T22:00Z",
          "url_espn": "https://www.espn.com.ar/futbol/partido/_/juegoId/401860124/athletic-vila-nova"
        }
      ]
    },
    {
      "liga": "Liga Profesional Argentina",
      "liga_slug": "arg.1",
      "prioridad": 120,
      "total": 3,
      "partidos": [
        {
          "id": "762895",
          "partido": "Gimnasia (Mendoza) vs Defensa y Justicia",
          "local": "Gimnasia (Mendoza)",
          "visitante": "Defensa y Justicia",
          "local_id": "11972",
          "visitante_id": "8950",
          "local_logo": "https://a.espncdn.com/i/teamlogos/soccer/500/11972.png",
          "visitante_logo": "https://a.espncdn.com/i/teamlogos/soccer/500/8950.png",
          "liga": "Liga Profesional Argentina",
          "liga_corta": "Liga Profesional Argentina",
          "liga_slug": "arg.1",
          "prioridad_liga": 120,
          "competicion": {
            "nombre": "Liga Profesional Argentina",
            "nombre_corto": "Liga Profesional Argentina",
            "slug": "arg.1",
            "prioridad": 120
          },
          "fecha": "2026-05-04",
          "hora_inicio": "17:00",
          "hora": "Fin",
          "mostrar_tiempo": "Fin",
          "estado": "Tiempo Completo",
          "estado_corto": "F",
          "estado_nombre": "STATUS_FULL_TIME",
          "completado": true,
          "minuto": null,
          "periodo": null,
          "marcador_local": "2",
          "marcador_visitante": "1",
          "resultado": "2-1",
          "mostrar_marcador": true,
          "goleadores": [],
          "fecha_espn": "2026-05-04T20:00Z",
          "url_espn": "https://www.espn.com.ar/futbol/partido/_/juegoId/762895"
        },
        {
          "id": "762903",
          "partido": "Vélez Sarsfield vs Newell's Old Boys",
          "local": "Vélez Sarsfield",
          "visitante": "Newell's Old Boys",
          "local_id": "21",
          "visitante_id": "14",
          "local_logo": "https://a.espncdn.com/i/teamlogos/soccer/500/21.png",
          "visitante_logo": "https://a.espncdn.com/i/teamlogos/soccer/500/14.png",
          "liga": "Liga Profesional Argentina",
          "liga_corta": "Liga Profesional Argentina",
          "liga_slug": "arg.1",
          "prioridad_liga": 120,
          "competicion": {
            "nombre": "Liga Profesional Argentina",
            "nombre_corto": "Liga Profesional Argentina",
            "slug": "arg.1",
            "prioridad": 120
          },
          "fecha": "2026-05-04",
          "hora_inicio": "19:15",
          "hora": "19'",
          "mostrar_tiempo": "19'",
          "estado": "First Half",
          "estado_corto": "19'",
          "estado_nombre": "STATUS_FIRST_HALF",
          "completado": false,
          "minuto": "19'",
          "periodo": 1,
          "marcador_local": "0",
          "marcador_visitante": "0",
          "resultado": "0-0",
          "mostrar_marcador": true,
          "goleadores": [],
          "fecha_espn": "2026-05-04T22:15Z",
          "url_espn": "https://www.espn.com.ar/futbol/partido/_/juegoId/762903/newells-old-boys-velez-sarsfield"
        },
        {
          "id": "762908",
          "partido": "Estudiantes de Río Cuarto vs Instituto (Córdoba)",
          "local": "Estudiantes de Río Cuarto",
          "visitante": "Instituto (Córdoba)",
          "local_id": "19685",
          "visitante_id": "2975",
          "local_logo": "https://a.espncdn.com/i/teamlogos/soccer/500/19685.png",
          "visitante_logo": "https://a.espncdn.com/i/teamlogos/soccer/500/2975.png",
          "liga": "Liga Profesional Argentina",
          "liga_corta": "Liga Profesional Argentina",
          "liga_slug": "arg.1",
          "prioridad_liga": 120,
          "competicion": {
            "nombre": "Liga Profesional Argentina",
            "nombre_corto": "Liga Profesional Argentina",
            "slug": "arg.1",
            "prioridad": 120
          },
          "fecha": "2026-05-04",
          "hora_inicio": "21:30",
          "hora": "0'",
          "mostrar_tiempo": "0'",
          "estado": "Agendado",
          "estado_corto": "Scheduled",
          "estado_nombre": "STATUS_SCHEDULED",
          "completado": false,
          "minuto": "0'",
          "periodo": null,
          "marcador_local": null,
          "marcador_visitante": null,
          "resultado": null,
          "mostrar_marcador": false,
          "goleadores": [],
          "fecha_espn": "2026-05-05T00:30Z",
          "url_espn": "https://www.espn.com.ar/futbol/partido/_/juegoId/762908/instituto-cordoba-estudiantes-de-rio-cuarto"
        }
      ]
    },
    {
      "liga": "Primera Nacional Argentina",
      "liga_slug": "arg.2",
      "prioridad": 123,
      "total": 2,
      "partidos": [
        {
          "id": "401843818",
          "partido": "Quilmes vs Chacarita Juniors",
          "local": "Quilmes",
          "visitante": "Chacarita Juniors",
          "local_id": "2741",
          "visitante_id": "6",
          "local_logo": "https://a.espncdn.com/i/teamlogos/soccer/500/2741.png",
          "visitante_logo": "https://a.espncdn.com/i/teamlogos/soccer/500/6.png",
          "liga": "Primera Nacional Argentina",
          "liga_corta": "Primera Nacional Argentina",
          "liga_slug": "arg.2",
          "prioridad_liga": 123,
          "competicion": {
            "nombre": "Primera Nacional Argentina",
            "nombre_corto": "Primera Nacional Argentina",
            "slug": "arg.2",
            "prioridad": 123
          },
          "fecha": "2026-05-04",
          "hora_inicio": "20:00",
          "hora": "0'",
          "mostrar_tiempo": "0'",
          "estado": "Agendado",
          "estado_corto": "Scheduled",
          "estado_nombre": "STATUS_SCHEDULED",
          "completado": false,
          "minuto": "0'",
          "periodo": null,
          "marcador_local": null,
          "marcador_visitante": null,
          "resultado": null,
          "mostrar_marcador": false,
          "goleadores": [],
          "fecha_espn": "2026-05-04T23:00Z",
          "url_espn": "https://www.espn.com.ar/futbol/partido/_/juegoId/401843818/chacarita-juniors-quilmes"
        },
        {
          "id": "401843813",
          "partido": "Gimnasia y Tiro (Salta) vs Agropecuario",
          "local": "Gimnasia y Tiro (Salta)",
          "visitante": "Agropecuario",
          "local_id": "10743",
          "visitante_id": "13913",
          "local_logo": "https://a.espncdn.com/i/teamlogos/soccer/500/10743.png",
          "visitante_logo": "https://a.espncdn.com/i/teamlogos/soccer/500/13913.png",
          "liga": "Primera Nacional Argentina",
          "liga_corta": "Primera Nacional Argentina",
          "liga_slug": "arg.2",
          "prioridad_liga": 123,
          "competicion": {
            "nombre": "Primera Nacional Argentina",
            "nombre_corto": "Primera Nacional Argentina",
            "slug": "arg.2",
            "prioridad": 123
          },
          "fecha": "2026-05-04",
          "hora_inicio": "21:30",
          "hora": "0'",
          "mostrar_tiempo": "0'",
          "estado": "Agendado",
          "estado_corto": "Scheduled",
          "estado_nombre": "STATUS_SCHEDULED",
          "completado": false,
          "minuto": "0'",
          "periodo": null,
          "marcador_local": null,
          "marcador_visitante": null,
          "resultado": null,
          "mostrar_marcador": false,
          "goleadores": [],
          "fecha_espn": "2026-05-05T00:30Z",
          "url_espn": "https://www.espn.com.ar/futbol/partido/_/juegoId/401843813/agropecuario-gimnasia-y-tiro-salta"
        }
      ]
    },
    {
      "liga": "Primera División Uruguay",
      "liga_slug": "uru.1",
      "prioridad": 130,
      "total": 1,
      "partidos": [
        {
          "id": "401861858",
          "partido": "Peñarol vs Defensor Sporting",
          "local": "Peñarol",
          "visitante": "Defensor Sporting",
          "local_id": "2683",
          "visitante_id": "1007",
          "local_logo": "https://a.espncdn.com/i/teamlogos/soccer/500/2683.png",
          "visitante_logo": "https://a.espncdn.com/i/teamlogos/soccer/500/1007.png",
          "liga": "Primera División Uruguay",
          "liga_corta": "Primera División Uruguay",
          "liga_slug": "uru.1",
          "prioridad_liga": 130,
          "competicion": {
            "nombre": "Primera División Uruguay",
            "nombre_corto": "Primera División Uruguay",
            "slug": "uru.1",
            "prioridad": 130
          },
          "fecha": "2026-05-04",
          "hora_inicio": "19:30",
          "hora": "0'",
          "mostrar_tiempo": "0'",
          "estado": "Agendado",
          "estado_corto": "Scheduled",
          "estado_nombre": "STATUS_SCHEDULED",
          "completado": false,
          "minuto": "0'",
          "periodo": null,
          "marcador_local": null,
          "marcador_visitante": null,
          "resultado": null,
          "mostrar_marcador": false,
          "goleadores": [],
          "fecha_espn": "2026-05-04T22:30Z",
          "url_espn": "https://www.espn.com.ar/futbol/partido/_/juegoId/401861858/defensor-sporting-penarol"
        }
      ]
    },
    {
      "liga": "Liga 1 Perú",
      "liga_slug": "per.1",
      "prioridad": 134,
      "total": 1,
      "partidos": [
        {
          "id": "401857482",
          "partido": "Los Chankas vs Deportivo Garcilaso",
          "local": "Los Chankas",
          "visitante": "Deportivo Garcilaso",
          "local_id": "22168",
          "visitante_id": "21819",
          "local_logo": "https://a.espncdn.com/i/teamlogos/soccer/500/22168.png",
          "visitante_logo": "https://a.espncdn.com/i/teamlogos/soccer/500/21819.png",
          "liga": "Liga 1 Perú",
          "liga_corta": "Liga 1 Perú",
          "liga_slug": "per.1",
          "prioridad_liga": 134,
          "competicion": {
            "nombre": "Liga 1 Perú",
            "nombre_corto": "Liga 1 Perú",
            "slug": "per.1",
            "prioridad": 134
          },
          "fecha": "2026-05-04",
          "hora_inicio": "15:00",
          "hora": "Fin",
          "mostrar_tiempo": "Fin",
          "estado": "Tiempo Completo",
          "estado_corto": "F",
          "estado_nombre": "STATUS_FULL_TIME",
          "completado": true,
          "minuto": null,
          "periodo": null,
          "marcador_local": "0",
          "marcador_visitante": "1",
          "resultado": "0-1",
          "mostrar_marcador": true,
          "goleadores": [],
          "fecha_espn": "2026-05-04T18:00Z",
          "url_espn": "https://www.espn.com.ar/futbol/partido/_/juegoId/401857482/deportivo-garcilaso-los-chankas"
        }
      ]
    },
    {
      "liga": "Primera División Bolivia",
      "liga_slug": "bol.1",
      "prioridad": 136,
      "total": 1,
      "partidos": [
        {
          "id": "401866921",
          "partido": "Universitario de Vinto vs Blooming",
          "local": "Universitario de Vinto",
          "visitante": "Blooming",
          "local_id": "21379",
          "visitante_id": "6047",
          "local_logo": "https://a.espncdn.com/i/teamlogos/soccer/500/21379.png",
          "visitante_logo": "https://a.espncdn.com/i/teamlogos/soccer/500/6047.png",
          "liga": "Primera División Bolivia",
          "liga_corta": "Primera División Bolivia",
          "liga_slug": "bol.1",
          "prioridad_liga": 136,
          "competicion": {
            "nombre": "Primera División Bolivia",
            "nombre_corto": "Primera División Bolivia",
            "slug": "bol.1",
            "prioridad": 136
          },
          "fecha": "2026-05-04",
          "hora_inicio": "21:00",
          "hora": "0'",
          "mostrar_tiempo": "0'",
          "estado": "Agendado",
          "estado_corto": "Scheduled",
          "estado_nombre": "STATUS_SCHEDULED",
          "completado": false,
          "minuto": "0'",
          "periodo": null,
          "marcador_local": null,
          "marcador_visitante": null,
          "resultado": null,
          "mostrar_marcador": false,
          "goleadores": [],
          "fecha_espn": "2026-05-05T00:00Z",
          "url_espn": "https://www.espn.com.ar/futbol/partido/_/juegoId/401866921/blooming-universitario-de-vinto"
        }
      ]
    },
    {
      "liga": "Saudi Pro League",
      "liga_slug": "ksa.1",
      "prioridad": 310,
      "total": 3,
      "partidos": [
        {
          "id": "756177",
          "partido": "Al Fayha vs Al Riyadh",
          "local": "Al Fayha",
          "visitante": "Al Riyadh",
          "local_id": "21827",
          "visitante_id": "21965",
          "local_logo": "https://a.espncdn.com/i/teamlogos/soccer/500/21827.png",
          "visitante_logo": "https://a.espncdn.com/i/teamlogos/soccer/500/21965.png",
          "liga": "Saudi Pro League",
          "liga_corta": "Saudi Pro League",
          "liga_slug": "ksa.1",
          "prioridad_liga": 310,
          "competicion": {
            "nombre": "Saudi Pro League",
            "nombre_corto": "Saudi Pro League",
            "slug": "ksa.1",
            "prioridad": 310
          },
          "fecha": "2026-05-04",
          "hora_inicio": "13:10",
          "hora": "Fin",
          "mostrar_tiempo": "Fin",
          "estado": "Tiempo Completo",
          "estado_corto": "F",
          "estado_nombre": "STATUS_FULL_TIME",
          "completado": true,
          "minuto": null,
          "periodo": null,
          "marcador_local": "4",
          "marcador_visitante": "2",
          "resultado": "4-2",
          "mostrar_marcador": true,
          "goleadores": [],
          "fecha_espn": "2026-05-04T16:10Z",
          "url_espn": "https://www.espn.com.ar/futbol/partido/_/juegoId/756177/al-riyadh-al-fayha"
        },
        {
          "id": "756174",
          "partido": "Al Ettifaq vs Al Najma",
          "local": "Al Ettifaq",
          "visitante": "Al Najma",
          "local_id": "8363",
          "visitante_id": "22023",
          "local_logo": "https://a.espncdn.com/i/teamlogos/soccer/500/8363.png",
          "visitante_logo": "https://a.espncdn.com/i/teamlogos/soccer/500/22023.png",
          "liga": "Saudi Pro League",
          "liga_corta": "Saudi Pro League",
          "liga_slug": "ksa.1",
          "prioridad_liga": 310,
          "competicion": {
            "nombre": "Saudi Pro League",
            "nombre_corto": "Saudi Pro League",
            "slug": "ksa.1",
            "prioridad": 310
          },
          "fecha": "2026-05-04",
          "hora_inicio": "15:00",
          "hora": "Fin",
          "mostrar_tiempo": "Fin",
          "estado": "Tiempo Completo",
          "estado_corto": "F",
          "estado_nombre": "STATUS_FULL_TIME",
          "completado": true,
          "minuto": null,
          "periodo": null,
          "marcador_local": "0",
          "marcador_visitante": "0",
          "resultado": "0-0",
          "mostrar_marcador": true,
          "goleadores": [],
          "fecha_espn": "2026-05-04T18:00Z",
          "url_espn": "https://www.espn.com.ar/futbol/partido/_/juegoId/756174/al-najma-al-ettifaq"
        },
        {
          "id": "756179",
          "partido": "Al Ittihad vs Al Kholood",
          "local": "Al Ittihad",
          "visitante": "Al Kholood",
          "local_id": "2276",
          "visitante_id": "22028",
          "local_logo": "https://a.espncdn.com/i/teamlogos/soccer/500/2276.png",
          "visitante_logo": "https://a.espncdn.com/i/teamlogos/soccer/500/22028.png",
          "liga": "Saudi Pro League",
          "liga_corta": "Saudi Pro League",
          "liga_slug": "ksa.1",
          "prioridad_liga": 310,
          "competicion": {
            "nombre": "Saudi Pro League",
            "nombre_corto": "Saudi Pro League",
            "slug": "ksa.1",
            "prioridad": 310
          },
          "fecha": "2026-05-04",
          "hora_inicio": "15:00",
          "hora": "Fin",
          "mostrar_tiempo": "Fin",
          "estado": "Tiempo Completo",
          "estado_corto": "F",
          "estado_nombre": "STATUS_FULL_TIME",
          "completado": true,
          "minuto": null,
          "periodo": null,
          "marcador_local": "0",
          "marcador_visitante": "0",
          "resultado": "0-0",
          "mostrar_marcador": true,
          "goleadores": [],
          "fecha_espn": "2026-05-04T18:00Z",
          "url_espn": "https://www.espn.com.ar/futbol/partido/_/juegoId/756179/al-kholood-al-ittihad"
        }
      ]
    },
    {
      "liga": "Women's Super League Inglaterra",
      "liga_slug": "eng.w.1",
      "prioridad": 503,
      "total": 1,
      "partidos": [
        {
          "id": "754418",
          "partido": "Aston Villa vs West Ham United",
          "local": "Aston Villa",
          "visitante": "West Ham United",
          "local_id": "20707",
          "visitante_id": "19975",
          "local_logo": "https://a.espncdn.com/i/teamlogos/soccer/500/20707.png",
          "visitante_logo": "https://a.espncdn.com/i/teamlogos/soccer/500/19975.png",
          "liga": "Women's Super League Inglaterra",
          "liga_corta": "Women's Super League Inglaterra",
          "liga_slug": "eng.w.1",
          "prioridad_liga": 503,
          "competicion": {
            "nombre": "Women's Super League Inglaterra",
            "nombre_corto": "Women's Super League Inglaterra",
            "slug": "eng.w.1",
            "prioridad": 503
          },
          "fecha": "2026-05-04",
          "hora_inicio": "09:00",
          "hora": "Fin",
          "mostrar_tiempo": "Fin",
          "estado": "Tiempo Completo",
          "estado_corto": "F",
          "estado_nombre": "STATUS_FULL_TIME",
          "completado": true,
          "minuto": null,
          "periodo": null,
          "marcador_local": "0",
          "marcador_visitante": "2",
          "resultado": "0-2",
          "mostrar_marcador": true,
          "goleadores": [],
          "fecha_espn": "2026-05-04T12:00Z",
          "url_espn": "https://www.espn.com.ar/futbol/partido/_/juegoId/754418/west-ham-united-aston-villa"
        }
      ]
    },
    {
      "liga": "Allsvenskan Suecia",
      "liga_slug": "swe.1",
      "prioridad": 9999,
      "total": 2,
      "partidos": [
        {
          "id": "401842699",
          "partido": "Djurgården vs IFK Göteborg",
          "local": "Djurgården",
          "visitante": "IFK Göteborg",
          "local_id": "2339",
          "visitante_id": "2556",
          "local_logo": "https://a.espncdn.com/i/teamlogos/soccer/500/2339.png",
          "visitante_logo": "https://a.espncdn.com/i/teamlogos/soccer/500/2556.png",
          "liga": "Allsvenskan Suecia",
          "liga_corta": "Allsvenskan Suecia",
          "liga_slug": "swe.1",
          "prioridad_liga": 9999,
          "competicion": {
            "nombre": "Allsvenskan Suecia",
            "nombre_corto": "Allsvenskan Suecia",
            "slug": "swe.1",
            "prioridad": 9999
          },
          "fecha": "2026-05-04",
          "hora_inicio": "14:00",
          "hora": "Fin",
          "mostrar_tiempo": "Fin",
          "estado": "Tiempo Completo",
          "estado_corto": "F",
          "estado_nombre": "STATUS_FULL_TIME",
          "completado": true,
          "minuto": null,
          "periodo": null,
          "marcador_local": "6",
          "marcador_visitante": "0",
          "resultado": "6-0",
          "mostrar_marcador": true,
          "goleadores": [],
          "fecha_espn": "2026-05-04T17:00Z",
          "url_espn": "https://www.espn.com.ar/futbol/partido/_/juegoId/401842699/ifk-goteborg-djurgarden"
        },
        {
          "id": "401842703",
          "partido": "Halmstads BK vs IF Brommapojkarna",
          "local": "Halmstads BK",
          "visitante": "IF Brommapojkarna",
          "local_id": "3017",
          "visitante_id": "8221",
          "local_logo": "https://a.espncdn.com/i/teamlogos/soccer/500/3017.png",
          "visitante_logo": "https://a.espncdn.com/i/teamlogos/soccer/500/8221.png",
          "liga": "Allsvenskan Suecia",
          "liga_corta": "Allsvenskan Suecia",
          "liga_slug": "swe.1",
          "prioridad_liga": 9999,
          "competicion": {
            "nombre": "Allsvenskan Suecia",
            "nombre_corto": "Allsvenskan Suecia",
            "slug": "swe.1",
            "prioridad": 9999
          },
          "fecha": "2026-05-04",
          "hora_inicio": "14:00",
          "hora": "Fin",
          "mostrar_tiempo": "Fin",
          "estado": "Tiempo Completo",
          "estado_corto": "F",
          "estado_nombre": "STATUS_FULL_TIME",
          "completado": true,
          "minuto": null,
          "periodo": null,
          "marcador_local": "1",
          "marcador_visitante": "3",
          "resultado": "1-3",
          "mostrar_marcador": true,
          "goleadores": [],
          "fecha_espn": "2026-05-04T17:00Z",
          "url_espn": "https://www.espn.com.ar/futbol/partido/_/juegoId/401842703/if-brommapojkarna-halmstads-bk"
        }
      ]
    },
    {
      "liga": "Eliteserien Noruega",
      "liga_slug": "nor.1",
      "prioridad": 9999,
      "total": 1,
      "partidos": [
        {
          "id": "401843333",
          "partido": "Bodo/Glimt vs Molde",
          "local": "Bodo/Glimt",
          "visitante": "Molde",
          "local_id": "2980",
          "visitante_id": "2715",
          "local_logo": "https://a.espncdn.com/i/teamlogos/soccer/500/2980.png",
          "visitante_logo": "https://a.espncdn.com/i/teamlogos/soccer/500/2715.png",
          "liga": "Eliteserien Noruega",
          "liga_corta": "Eliteserien Noruega",
          "liga_slug": "nor.1",
          "prioridad_liga": 9999,
          "competicion": {
            "nombre": "Eliteserien Noruega",
            "nombre_corto": "Eliteserien Noruega",
            "slug": "nor.1",
            "prioridad": 9999
          },
          "fecha": "2026-05-04",
          "hora_inicio": "14:00",
          "hora": "Fin",
          "mostrar_tiempo": "Fin",
          "estado": "Tiempo Completo",
          "estado_corto": "F",
          "estado_nombre": "STATUS_FULL_TIME",
          "completado": true,
          "minuto": null,
          "periodo": null,
          "marcador_local": "0",
          "marcador_visitante": "1",
          "resultado": "0-1",
          "mostrar_marcador": true,
          "goleadores": [],
          "fecha_espn": "2026-05-04T17:00Z",
          "url_espn": "https://www.espn.com.ar/futbol/partido/_/juegoId/401843333"
        }
      ]
    },
    {
      "liga": "Indian Super League",
      "liga_slug": "ind.1",
      "prioridad": 9999,
      "total": 1,
      "partidos": [
        {
          "id": "401860516",
          "partido": "Odisha FC vs Bengaluru FC",
          "local": "Odisha FC",
          "visitante": "Bengaluru FC",
          "local_id": "17998",
          "visitante_id": "18851",
          "local_logo": "https://a.espncdn.com/i/teamlogos/soccer/500/17998.png",
          "visitante_logo": "https://a.espncdn.com/i/teamlogos/soccer/500/18851.png",
          "liga": "Indian Super League",
          "liga_corta": "Indian Super League",
          "liga_slug": "ind.1",
          "prioridad_liga": 9999,
          "competicion": {
            "nombre": "Indian Super League",
            "nombre_corto": "Indian Super League",
            "slug": "ind.1",
            "prioridad": 9999
          },
          "fecha": "2026-05-04",
          "hora_inicio": "11:00",
          "hora": "Fin",
          "mostrar_tiempo": "Fin",
          "estado": "Tiempo Completo",
          "estado_corto": "F",
          "estado_nombre": "STATUS_FULL_TIME",
          "completado": true,
          "minuto": null,
          "periodo": null,
          "marcador_local": "1",
          "marcador_visitante": "1",
          "resultado": "1-1",
          "mostrar_marcador": true,
          "goleadores": [],
          "fecha_espn": "2026-05-04T14:00Z",
          "url_espn": "https://www.espn.com.ar/futbol/partido/_/juegoId/401860516/bengaluru-fc-odisha-fc"
        }
      ]
    },
    {
      "liga": "Premier Division Irlanda",
      "liga_slug": "irl.1",
      "prioridad": 9999,
      "total": 5,
      "partidos": [
        {
          "id": "763106",
          "partido": "Bohemians vs Shelbourne",
          "local": "Bohemians",
          "visitante": "Shelbourne",
          "local_id": "615",
          "visitante_id": "20297",
          "local_logo": "https://a.espncdn.com/i/teamlogos/soccer/500/615.png",
          "visitante_logo": "https://a.espncdn.com/i/teamlogos/soccer/500/20297.png",
          "liga": "Premier Division Irlanda",
          "liga_corta": "Premier Division Irlanda",
          "liga_slug": "irl.1",
          "prioridad_liga": 9999,
          "competicion": {
            "nombre": "Premier Division Irlanda",
            "nombre_corto": "Premier Division Irlanda",
            "slug": "irl.1",
            "prioridad": 9999
          },
          "fecha": "2026-05-04",
          "hora_inicio": "13:00",
          "hora": "Fin",
          "mostrar_tiempo": "Fin",
          "estado": "Tiempo Completo",
          "estado_corto": "F",
          "estado_nombre": "STATUS_FULL_TIME",
          "completado": true,
          "minuto": null,
          "periodo": null,
          "marcador_local": "2",
          "marcador_visitante": "2",
          "resultado": "2-2",
          "mostrar_marcador": true,
          "goleadores": [],
          "fecha_espn": "2026-05-04T16:00Z",
          "url_espn": "https://www.espn.com.ar/futbol/partido/_/juegoId/763106/shelbourne-bohemians"
        },
        {
          "id": "763105",
          "partido": "Derry City vs Galway Utd",
          "local": "Derry City",
          "visitante": "Galway Utd",
          "local_id": "2712",
          "visitante_id": "7587",
          "local_logo": "https://a.espncdn.com/i/teamlogos/soccer/500/2712.png",
          "visitante_logo": "https://a.espncdn.com/i/teamlogos/soccer/500/7587.png",
          "liga": "Premier Division Irlanda",
          "liga_corta": "Premier Division Irlanda",
          "liga_slug": "irl.1",
          "prioridad_liga": 9999,
          "competicion": {
            "nombre": "Premier Division Irlanda",
            "nombre_corto": "Premier Division Irlanda",
            "slug": "irl.1",
            "prioridad": 9999
          },
          "fecha": "2026-05-04",
          "hora_inicio": "13:00",
          "hora": "Fin",
          "mostrar_tiempo": "Fin",
          "estado": "Tiempo Completo",
          "estado_corto": "F",
          "estado_nombre": "STATUS_FULL_TIME",
          "completado": true,
          "minuto": null,
          "periodo": null,
          "marcador_local": "1",
          "marcador_visitante": "1",
          "resultado": "1-1",
          "mostrar_marcador": true,
          "goleadores": [],
          "fecha_espn": "2026-05-04T16:00Z",
          "url_espn": "https://www.espn.com.ar/futbol/partido/_/juegoId/763105/galway-utd-derry-city"
        },
        {
          "id": "763107",
          "partido": "Shamrock Rovers vs Drogheda Utd",
          "local": "Shamrock Rovers",
          "visitante": "Drogheda Utd",
          "local_id": "2564",
          "visitante_id": "6741",
          "local_logo": "https://a.espncdn.com/i/teamlogos/soccer/500/2564.png",
          "visitante_logo": "https://a.espncdn.com/i/teamlogos/soccer/500/6741.png",
          "liga": "Premier Division Irlanda",
          "liga_corta": "Premier Division Irlanda",
          "liga_slug": "irl.1",
          "prioridad_liga": 9999,
          "competicion": {
            "nombre": "Premier Division Irlanda",
            "nombre_corto": "Premier Division Irlanda",
            "slug": "irl.1",
            "prioridad": 9999
          },
          "fecha": "2026-05-04",
          "hora_inicio": "13:00",
          "hora": "Fin",
          "mostrar_tiempo": "Fin",
          "estado": "Tiempo Completo",
          "estado_corto": "F",
          "estado_nombre": "STATUS_FULL_TIME",
          "completado": true,
          "minuto": null,
          "periodo": null,
          "marcador_local": "4",
          "marcador_visitante": "1",
          "resultado": "4-1",
          "mostrar_marcador": true,
          "goleadores": [],
          "fecha_espn": "2026-05-04T16:00Z",
          "url_espn": "https://www.espn.com.ar/futbol/partido/_/juegoId/763107/drogheda-utd-shamrock-rovers"
        },
        {
          "id": "763109",
          "partido": "Sligo vs St Patricks Athletic",
          "local": "Sligo",
          "visitante": "St Patricks Athletic",
          "local_id": "7601",
          "visitante_id": "7588",
          "local_logo": "https://a.espncdn.com/i/teamlogos/soccer/500/7601.png",
          "visitante_logo": "https://a.espncdn.com/i/teamlogos/soccer/500/7588.png",
          "liga": "Premier Division Irlanda",
          "liga_corta": "Premier Division Irlanda",
          "liga_slug": "irl.1",
          "prioridad_liga": 9999,
          "competicion": {
            "nombre": "Premier Division Irlanda",
            "nombre_corto": "Premier Division Irlanda",
            "slug": "irl.1",
            "prioridad": 9999
          },
          "fecha": "2026-05-04",
          "hora_inicio": "13:00",
          "hora": "Fin",
          "mostrar_tiempo": "Fin",
          "estado": "Tiempo Completo",
          "estado_corto": "F",
          "estado_nombre": "STATUS_FULL_TIME",
          "completado": true,
          "minuto": null,
          "periodo": null,
          "marcador_local": "1",
          "marcador_visitante": "1",
          "resultado": "1-1",
          "mostrar_marcador": true,
          "goleadores": [],
          "fecha_espn": "2026-05-04T16:00Z",
          "url_espn": "https://www.espn.com.ar/futbol/partido/_/juegoId/763109/st-patricks-athletic-sligo"
        },
        {
          "id": "763108",
          "partido": "Waterford vs Dundalk",
          "local": "Waterford",
          "visitante": "Dundalk",
          "local_id": "18968",
          "visitante_id": "2559",
          "local_logo": "https://a.espncdn.com/i/teamlogos/soccer/500/18968.png",
          "visitante_logo": "https://a.espncdn.com/i/teamlogos/soccer/500/2559.png",
          "liga": "Premier Division Irlanda",
          "liga_corta": "Premier Division Irlanda",
          "liga_slug": "irl.1",
          "prioridad_liga": 9999,
          "competicion": {
            "nombre": "Premier Division Irlanda",
            "nombre_corto": "Premier Division Irlanda",
            "slug": "irl.1",
            "prioridad": 9999
          },
          "fecha": "2026-05-04",
          "hora_inicio": "13:00",
          "hora": "Fin",
          "mostrar_tiempo": "Fin",
          "estado": "Tiempo Completo",
          "estado_corto": "F",
          "estado_nombre": "STATUS_FULL_TIME",
          "completado": true,
          "minuto": null,
          "periodo": null,
          "marcador_local": "3",
          "marcador_visitante": "3",
          "resultado": "3-3",
          "mostrar_marcador": true,
          "goleadores": [],
          "fecha_espn": "2026-05-04T16:00Z",
          "url_espn": "https://www.espn.com.ar/futbol/partido/_/juegoId/763108/dundalk-waterford"
        }
      ]
    },
    {
      "liga": "Superliga Dinamarca",
      "liga_slug": "den.1",
      "prioridad": 9999,
      "total": 1,
      "partidos": [
        {
          "id": "401863674",
          "partido": "FC Midtjylland vs Viborg FF",
          "local": "FC Midtjylland",
          "visitante": "Viborg FF",
          "local_id": "572",
          "visitante_id": "3153",
          "local_logo": "https://a.espncdn.com/i/teamlogos/soccer/500/572.png",
          "visitante_logo": "https://a.espncdn.com/i/teamlogos/soccer/500/3153.png",
          "liga": "Superliga Dinamarca",
          "liga_corta": "Superliga Dinamarca",
          "liga_slug": "den.1",
          "prioridad_liga": 9999,
          "competicion": {
            "nombre": "Superliga Dinamarca",
            "nombre_corto": "Superliga Dinamarca",
            "slug": "den.1",
            "prioridad": 9999
          },
          "fecha": "2026-05-04",
          "hora_inicio": "14:00",
          "hora": "Fin",
          "mostrar_tiempo": "Fin",
          "estado": "Tiempo Completo",
          "estado_corto": "F",
          "estado_nombre": "STATUS_FULL_TIME",
          "completado": true,
          "minuto": null,
          "periodo": null,
          "marcador_local": "3",
          "marcador_visitante": "3",
          "resultado": "3-3",
          "mostrar_marcador": true,
          "goleadores": [],
          "fecha_espn": "2026-05-04T17:00Z",
          "url_espn": "https://www.espn.com.ar/futbol/partido/_/juegoId/401863674"
        }
      ]
    }
  ],
  "errores": [
    {
      "liga": "Community Shield",
      "slug": "eng.community",
      "error": "400 Client Error: Bad Request for url: https://site.web.api.espn.com/apis/site/v2/sports/soccer/eng.community/scoreboard?region=ar&lang=es&contentorigin=espn&dates=20260504&limit=300&_=1777934339"
    },
    {
      "liga": "3. Liga",
      "slug": "ger.3",
      "error": "400 Client Error: Bad Request for url: https://site.web.api.espn.com/apis/site/v2/sports/soccer/ger.3/scoreboard?region=ar&lang=es&contentorigin=espn&dates=20260504&limit=300&_=1777934340"
    },
    {
      "liga": "KNVB Beker",
      "slug": "ned.knvb_beker",
      "error": "400 Client Error: Bad Request for url: https://site.web.api.espn.com/apis/site/v2/sports/soccer/ned.knvb_beker/scoreboard?region=ar&lang=es&contentorigin=espn&dates=20260504&limit=300&_=1777934340"
    },
    {
      "liga": "Liga Portugal 2",
      "slug": "por.2",
      "error": "400 Client Error: Bad Request for url: https://site.web.api.espn.com/apis/site/v2/sports/soccer/por.2/scoreboard?region=ar&lang=es&contentorigin=espn&dates=20260504&limit=300&_=1777934340"
    },
    {
      "liga": "Taça de Portugal",
      "slug": "por.taca_de_portugal",
      "error": "400 Client Error: Bad Request for url: https://site.web.api.espn.com/apis/site/v2/sports/soccer/por.taca_de_portugal/scoreboard?region=ar&lang=es&contentorigin=espn&dates=20260504&limit=300&_=1777934340"
    },
    {
      "liga": "Ekstraklasa Polonia",
      "slug": "pol.1",
      "error": "400 Client Error: Bad Request for url: https://site.web.api.espn.com/apis/site/v2/sports/soccer/pol.1/scoreboard?region=ar&lang=es&contentorigin=espn&dates=20260504&limit=300&_=1777934340"
    },
    {
      "liga": "HNL Croacia",
      "slug": "cro.1",
      "error": "400 Client Error: Bad Request for url: https://site.web.api.espn.com/apis/site/v2/sports/soccer/cro.1/scoreboard?region=ar&lang=es&contentorigin=espn&dates=20260504&limit=300&_=1777934340"
    },
    {
      "liga": "Liga I Rumania",
      "slug": "rom.1",
      "error": "400 Client Error: Bad Request for url: https://site.web.api.espn.com/apis/site/v2/sports/soccer/rom.1/scoreboard?region=ar&lang=es&contentorigin=espn&dates=20260504&limit=300&_=1777934340"
    },
    {
      "liga": "Premier League Ucrania",
      "slug": "ukr.1",
      "error": "400 Client Error: Bad Request for url: https://site.web.api.espn.com/apis/site/v2/sports/soccer/ukr.1/scoreboard?region=ar&lang=es&contentorigin=espn&dates=20260504&limit=300&_=1777934340"
    },
    {
      "liga": "USL Championship",
      "slug": "usa.2",
      "error": "400 Client Error: Bad Request for url: https://site.web.api.espn.com/apis/site/v2/sports/soccer/usa.2/scoreboard?region=ar&lang=es&contentorigin=espn&dates=20260504&limit=300&_=1777934340"
    },
    {
      "liga": "SuperLiga Serbia",
      "slug": "ser.1",
      "error": "400 Client Error: Bad Request for url: https://site.web.api.espn.com/apis/site/v2/sports/soccer/ser.1/scoreboard?region=ar&lang=es&contentorigin=espn&dates=20260504&limit=300&_=1777934340"
    },
    {
      "liga": "Copa MX",
      "slug": "mex.copa",
      "error": "400 Client Error: Bad Request for url: https://site.web.api.espn.com/apis/site/v2/sports/soccer/mex.copa/scoreboard?region=ar&lang=es&contentorigin=espn&dates=20260504&limit=300&_=1777934341"
    },
    {
      "liga": "CONCACAF Nations League",
      "slug": "concacaf.nations",
      "error": "400 Client Error: Bad Request for url: https://site.web.api.espn.com/apis/site/v2/sports/soccer/concacaf.nations/scoreboard?region=ar&lang=es&contentorigin=espn&dates=20260504&limit=300&_=1777934341"
    },
    {
      "liga": "J2 League Japón",
      "slug": "jpn.2",
      "error": "400 Client Error: Bad Request for url: https://site.web.api.espn.com/apis/site/v2/sports/soccer/jpn.2/scoreboard?region=ar&lang=es&contentorigin=espn&dates=20260504&limit=300&_=1777934341"
    },
    {
      "liga": "K League 1 Corea",
      "slug": "kor.1",
      "error": "400 Client Error: Bad Request for url: https://site.web.api.espn.com/apis/site/v2/sports/soccer/kor.1/scoreboard?region=ar&lang=es&contentorigin=espn&dates=20260504&limit=300&_=1777934341"
    },
    {
      "liga": "Qatar Stars League",
      "slug": "qat.1",
      "error": "400 Client Error: Bad Request for url: https://site.web.api.espn.com/apis/site/v2/sports/soccer/qat.1/scoreboard?region=ar&lang=es&contentorigin=espn&dates=20260504&limit=300&_=1777934341"
    },
    {
      "liga": "UAE Pro League",
      "slug": "uae.1",
      "error": "400 Client Error: Bad Request for url: https://site.web.api.espn.com/apis/site/v2/sports/soccer/uae.1/scoreboard?region=ar&lang=es&contentorigin=espn&dates=20260504&limit=300&_=1777934341"
    },
    {
      "liga": "Botola Marruecos",
      "slug": "mar.1",
      "error": "400 Client Error: Bad Request for url: https://site.web.api.espn.com/apis/site/v2/sports/soccer/mar.1/scoreboard?region=ar&lang=es&contentorigin=espn&dates=20260504&limit=300&_=1777934341"
    },
    {
      "liga": "Premier League Egipto",
      "slug": "egy.1",
      "error": "400 Client Error: Bad Request for url: https://site.web.api.espn.com/apis/site/v2/sports/soccer/egy.1/scoreboard?region=ar&lang=es&contentorigin=espn&dates=20260504&limit=300&_=1777934341"
    },
    {
      "liga": "Copa Intercontinental FIFA",
      "slug": "fifa.intercontinental",
      "error": "400 Client Error: Bad Request for url: https://site.web.api.espn.com/apis/site/v2/sports/soccer/fifa.intercontinental/scoreboard?region=ar&lang=es&contentorigin=espn&dates=20260504&limit=300&_=1777934341"
    }
  ]
}